Workbook

Sheet Instrucciones
A1: CÓMO CARGAR PRODUCTOS NUEVOS
A3: Esta planilla es el catálogo que usa el bot de WhatsApp para cotizar.
A4: Lo que carguen acá es lo que el bot va a poder responder.
A6: No tiene precios cerrados por cantidad: tiene el framework para calcular cualquier cantidad.
A7: Cada producto dice de qué material se hace, y el precio sale del material.
A9: LAS HOJAS Y PARA QUÉ SIRVEN
A11: Colecciones — las familias de productos. Su descripción encabeza el bloque que lee el bot.
A12: Productos — lo que se ofrece. La cantidad NO va acá: la pide el cliente.
A13: Materiales — precios y tramos. Un material sin escala por volumen = un solo tramo.
A14: Pendientes — para lo que NO encaja en este catálogo (ver más abajo).
A15: _listas — hoja OCULTA y AUTOMÁTICA. Se llena sola con lo que carguen en Materiales y
A16: en Colecciones. NO la abran ni escriban en ella: si escriben ahí, los
... A163: catálogo anterior, así que pueden cargar tranquilos.

Sheet Colecciones
A1: Colección | B1: Descripción | C1: Material base | D1: Sin mínimo por trabajo
A2: Stickers con forma | B2: Stickers y etiquetas cortados con forma, para uso en interior. Se imprimen en papel autoadhesivo brillo o en OPP (más resistente al roce y a la humedad, y disponible en holográfico, plata, cristal y mate). Se entregan troquelados sueltos o en plancha con medio corte, al mismo precio. Se cotizan por pliego A3. | C2: Papel autoadhesivo troquelado o medio corte
A3: Stickers para exterior | B3: Stickers y etiquetas cortados con forma, impresos en vinilo con tinta UV, que aguanta sol, lluvia y lavado. Para autos, cascos, heladeras, obradores y todo lo que quede a la intemperie. Se cotizan por metro cuadrado. | C3: Vinilo UV troquelado
A4: Carteles y vidrieras | B4: Impresión de gran formato para pared, vidrio o chapa. Adhesivos, que se pegan directo sobre la superficie, o rígidos, montados sobre plástico corrugado para que se sostengan solos. Para vidrieras hay además opciones de microperforado y esmerilado. Se cotizan por metro cuadrado. | C4: Vinilo y lona UV
A5: Banners y lonas | B5: Lona impresa full color con dobladillo y ojalillos, lista para colgar. Para el frente del local, eventos, ferias y publicidad en vía pública. Se cotizan por metro cuadrado. | C5: Lona
A6: Tarjetas personales | B6: Tarjetas de presentación 9x5 cm, full color. Simple o doble faz, en papel ilustración o kraft 280 g, con opción encapsulada (plastificada de ambos lados). Se cotizan por cantidad cerrada: 100, 500 o 1000. | C6: Tarjetas 9x5 simple faz x100
A7: Papelería comercial | B7: Papelería impresa con la marca del negocio: hojas membretadas, sobres, talonarios de factura o remito, notas de pedido, recetarios y carpetas institucionales.
A8: Impresión digital | B8: Impresión de archivos por hoja, en color o blanco y negro, A4 y A3. En papel obra, ilustración u opalina. El precio por hoja baja según la cantidad. | D8: sí
A9: Encuadernación y terminaciones | B9: Trabajos que se hacen sobre un impreso ya listo: anillado, wire-o, fresado, abrochado, laminado, plastificado, troquelado, ojalillos y numerado. Se cobran por unidad y no incluyen la impresión. | D9: sí
A10: Folletería y editorial | B10: Volantes, anotadores, apuntes y libros de estudio.
A11: Gran formato y cartelería | B11: Impresión de gran formato lista para usar: posters, porta banners tipo X y roll-up, y planos. También hay combos que traen la lona impresa junto con su estructura, a precio cerrado.
A12: Señalética y punto de venta | B12: Carteles de seguridad e higiene, cartas y menús plastificados, y carteles de precios para el local.
A13: Eventos y sociales | B13: Tarjetería para eventos: agradecimiento, invitaciones y afines.
A14: Diseño y servicios | B14: Servicios sobre archivos, sin impresión: escaneo y digitalización de planos y documentos en gran formato.

Sheet Productos
A1: Colección | B1: Producto | C1: Descripción | D1: Material | E1: Ancho (cm) | F1: Alto (cm) | G1: Piezas por unidad de cobro | H1: Sinónimos | I1: Formato
A2: Stickers con forma | B2: Stickers 3x3 cm | C2: Los más chicos. Papel autoadhesivo brillo. Troquelados sueltos o en plancha con medio corte, mismo precio. | D2: Papel autoadhesivo troquelado o medio corte | E2: 3 | F2: 3
A3: Stickers con forma | B3: Etiquetas para frascos 6x3 cm | C3: Formato alargado para frascos y botellas chicas. Papel autoadhesivo brillo. | D3: Papel autoadhesivo troquelado o medio corte | E3: 6 | F3: 3
A4: Stickers con forma | B4: Stickers 5x5 cm | C4: Impresión full color, corte con forma. Papel autoadhesivo brillo. Troquelados sueltos o en plancha con medio corte. | D4: Papel autoadhesivo troquelado o medio corte | E4: 5 | F4: 5
A5: Stickers con forma | B5: Stickers en OPP brillo 5x5 cm | C5: OPP brillo: más resistente al roce y a la humedad que el papel. | D5: OPP brillo troquelado | E5: 5 | F5: 5
A6: Stickers con forma | B6: Stickers holográficos 5x5 cm | C6: OPP tornasolado. También en plata, cristal y mate, al mismo precio. | D6: OPP plata, holográfico, cristal o mate troquelado | E6: 5 | F6: 5
A7: Stickers con forma | B7: Etiquetas 9x5 cm | C7: Tamaño tarjeta. Papel autoadhesivo brillo, full color. | D7: Papel autoadhesivo troquelado o medio corte | E7: 9 | F7: 5
A8: Stickers con forma | B8: Etiquetas en OPP brillo 9x5 cm | C8: Tamaño tarjeta en OPP brillo. | D8: OPP brillo troquelado | E8: 9 | F8: 5
A9: Stickers con forma | B9: Stickers 7x7 cm | C9: Impresión full color, corte con forma. Papel autoadhesivo brillo. | D9: Papel autoadhesivo troquelado o medio corte | E9: 7 | F9: 7
A10: Stickers con forma | B10: Stickers en OPP brillo 7x7 cm | C10: OPP brillo: más resistente al roce y a la humedad que el papel. | D10: OPP brillo troquelado | E10: 7 | F10: 7
A11: Stickers con forma | B11: Stickers holográficos 7x7 cm | C11: OPP tornasolado. También en plata, cristal y mate, al mismo precio. | D11: OPP plata, holográfico, cristal o mate troquelado | E11: 7 | F11: 7
A12: Stickers con forma | B12: Stickers 10x10 cm | C12: Impresión full color, corte con forma. Papel autoadhesivo brillo. | D12: Papel autoadhesivo troquelado o medio corte | E12: 10 | F12: 10
A13: Stickers con forma | B13: Stickers en OPP brillo 10x10 cm | C13: OPP brillo: más resistente al roce y a la humedad que el papel. | D13: OPP brillo troquelado | E13: 10 | F13: 10
... A32: Banners y lonas | B32: Banner de lona 4x1 m | C32: Lona impresa full color con dobladillo y ojalillos. | D32: Lona | E32: 400 | F32: 100
A33: Stickers con forma | B33: Stickers en plancha sin cortar | C33: La plancha impresa sin corte: el cliente recorta a mano. Papel autoadhesivo brillo. Sale más barato que el troquelado. | D33: Papel autoadhesivo solo impresión | E33: 5 | F33: 5 | H33: sin cortar, sin troquelar, plancha entera, solo impresión, recorto yo
A34: Stickers con forma | B34: Stickers en OPP brillo sin cortar | C34: Plancha de OPP brillo impresa sin corte. Más resistente al roce y a la humedad que el papel. | D34: OPP brillo | E34: 5 | F34: 5
A35: Stickers con forma | B35: Stickers holográficos sin cortar | C35: Plancha de OPP tornasolado impresa sin corte. También en plata, cristal y mate. | D35: OPP plata, holográfico, cristal o mate | E35: 5 | F35: 5
A36: Carteles y vidrieras | B36: Cartel adhesivo con blanco o barniz | C36: Vinilo UV con una capa de blanco o barniz: da más cuerpo al color sobre superficies oscuras o transparentes. | D36: Vinilo y lona UV con blanco o barniz | E36: 50 | F36: 70 | H36: con blanco, con barniz, para vidrio, para superficie oscura
A37: Tarjetas personales | B37: 100 tarjetas 9x5 cm simple faz | C37: Tarjetas de presentación full color, impresas de un lado. El precio es por las 100. | D37: Tarjetas 9x5 simple faz x100 | E37: 9 | F37: 5 | H37: tarjetas personales, tarjetas de presentación, tarjetas comerciales
A38: Tarjetas personales | B38: 100 tarjetas 9x5 cm simple faz encapsuladas | C38: Impresas de un lado y plastificadas de los dos: más resistentes y con mejor tacto. | D38: Tarjetas 9x5 simple faz encapsuladas x100 | E38: 9 | F38: 5
A39: Tarjetas personales | B39: 100 tarjetas 9x5 cm doble faz | C39: Full color de los dos lados. El precio es por las 100. | D39: Tarjetas 9x5 doble faz x100 | E39: 9 | F39: 5
A40: Tarjetas personales | B40: 100 tarjetas 9x5 cm doble faz encapsuladas | C40: Impresas de los dos lados y plastificadas. | D40: Tarjetas 9x5 doble faz encapsuladas x100 | E40: 9 | F40: 5
A41: Tarjetas personales | B41: 100 tarjetas 9x5 cm en papel kraft simple faz | C41: Papel kraft 280 g, con textura y color natural. Impresas de un lado. | D41: Tarjetas 9x5 kraft simple faz x100 | E41: 9 | F41: 5
A42: Tarjetas personales | B42: 100 tarjetas 9x5 cm en papel kraft doble faz | C42: Papel kraft 280 g, impresas de los dos lados. | D42: Tarjetas 9x5 kraft doble faz x100 | E42: 9 | F42: 5
A43: Tarjetas personales | B43: 500 tarjetas 9x5 cm simple faz | C43: Full color de un lado. El precio es por las 500. | D43: Tarjetas 9x5 simple faz x500 | E43: 9 | F43: 5
A44: Tarjetas personales | B44: 500 tarjetas 9x5 cm simple faz encapsuladas | C44: De un lado y plastificadas. El precio es por las 500. | D44: Tarjetas 9x5 simple faz encapsuladas x500 | E44: 9 | F44: 5
A45: Tarjetas personales | B45: 500 tarjetas 9x5 cm doble faz | C45: Full color de los dos lados. El precio es por las 500. | D45: Tarjetas 9x5 doble faz x500 | E45: 9 | F45: 5
A46: Tarjetas personales | B46: 500 tarjetas 9x5 cm doble faz encapsuladas | C46: De los dos lados y plastificadas. El precio es por las 500. | D46: Tarjetas 9x5 doble faz encapsuladas x500 | E46: 9 | F46: 5
A47: Tarjetas personales | B47: 1000 tarjetas 9x5 cm simple faz | C47: Full color de un lado. El precio es por las 1000. | D47: Tarjetas 9x5 simple faz x1000 | E47: 9 | F47: 5
A48: Tarjetas personales | B48: 1000 tarjetas 9x5 cm simple faz encapsuladas | C48: De un lado y plastificadas. El precio es por las 1000. | D48: Tarjetas 9x5 simple faz encapsuladas x1000 | E48: 9 | F48: 5
A49: Tarjetas personales | B49: 1000 tarjetas 9x5 cm doble faz | C49: Full color de los dos lados. El precio es por las 1000. | D49: Tarjetas 9x5 doble faz x1000 | E49: 9 | F49: 5
A50: Tarjetas personales | B50: 1000 tarjetas 9x5 cm doble faz encapsuladas | C50: De los dos lados y plastificadas. El precio es por las 1000. | D50: Tarjetas 9x5 doble faz encapsuladas x1000 | E50: 9 | F50: 5
A51: Papelería comercial | B51: 500 hojas membretadas A4 | C51: Hojas A4 impresas con el logo y los datos del negocio. El precio es por las 500. | D51: Hojas membretadas A4 x500 | H51: hojas membretadas, papel con logo, membrete | I51: A4
A52: Papelería comercial | B52: 100 sobres impresos | C52: Sobres con el logo y los datos del negocio. El precio es por los 100. | D52: Sobres impresos x100 | E52: 21 | F52: 11 | H52: sobres membretados, sobres con logo
A53: Papelería comercial | B53: 10 talonarios de factura o remito | C53: 10 talonarios A5 de 50 juegos por duplicado, abrochados y troquelados. El precio es por los 10 talonarios. | D53: Talonarios x10 | H53: talonarios, facturas, remitos, notas de pedido, comandas | I53: A5
A54: Papelería comercial | B54: Sobres oficio inglés | C54: Sobre tamaño oficio inglés impreso. Se cobra por unidad y el precio baja por cantidad. | D54: Sobres oficio inglés | E54: 23.5 | F54: 12 | H54: sobres, sobres oficio
A55: Papelería comercial | B55: Carpetas institucionales | C55: Carpeta de presentación A4 cerrada, en cartulina 300 g, troquelada, con solapa y ranura. Sin laminar. Se cobra por unidad. | D55: Carpetas institucionales sin laminar | H55: carpetas, carpetas de presentación, folders | I55: A4 cerrada
A56: Papelería comercial | B56: Carpetas institucionales laminadas | C56: La misma carpeta A4, plastificada: más resistente al uso y al roce. | D56: Carpetas institucionales laminadas | I56: A4 cerrada
A57: Papelería comercial | B57: Recetarios en negro | C57: Talonario de recetas impreso en negro. Mínimo 5 unidades. | D57: Recetarios en negro | H57: recetarios, recetas médicas, blocks de receta | I57: A5 o A6
A58: Papelería comercial | B58: Recetarios en color | C58: Talonario de recetas impreso full color. Mínimo 5 unidades. | D58: Recetarios en color | I58: A5 o A6
A59: Impresión digital | B59: Impresión color A4 | C59: Impresión full color en papel obra 75 g, de un lado. Se cobra por hoja y el precio baja por cantidad. | D59: Impresión color A4 simple faz | H59: imprimir, impresiones, copias en color | I59: A4
A60: Impresión digital | B60: Impresión color A4 doble faz | C60: Full color de los dos lados de la hoja. | D60: Impresión color A4 doble faz | I60: A4
A61: Impresión digital | B61: Impresión blanco y negro A4 | C61: Impresión en blanco y negro en papel obra 75 g, de un lado. Se cobra por hoja. | D61: Impresión blanco y negro A4 simple faz | H61: imprimir, impresiones, impresión de archivos, fotocopias | I61: A4
A62: Impresión digital | B62: Impresión blanco y negro A4 doble faz | C62: Blanco y negro de los dos lados de la hoja. Es lo que se usa para apuntes y material de estudio: se cuentan las hojas y se le suma el anillado. | D62: Impresión blanco y negro A4 doble faz | I62: A4
A63: Impresión digital | B63: Impresión color A3 | C63: Impresión láser full color en A3. Se cobra por hoja. | D63: Impresión color A3 | I63: A3
A64: Impresión digital | B64: Impresión blanco y negro A3 | C64: Impresión en blanco y negro en A3. Se cobra por hoja. | D64: Impresión blanco y negro A3 | I64: A3
A65: Impresión digital | B65: Impresión en papel ilustración | C65: Papel ilustración: más grueso y con terminación satinada. | D65: Impresión en papel ilustración | I65: A4
A66: Impresión digital | B66: Impresión en opalina | C66: Opalina: papel rígido y liso, para certificados y diplomas. | D66: Impresión en opalina | I66: A4
A67: Encuadernación y terminaciones | B67: Anillado plástico A4/Oficio | C67: Anillado con espiral plástico. Se cobra por unidad y no incluye la impresión. | D67: Anillado plástico A4/Oficio | H67: anillado, espiralado, espiral, encuadernado con anillo | I67: A4 u oficio
A68: Encuadernación y terminaciones | B68: Anillado metálico hasta 3/4 pulgada | C68: Anillado con espiral metálico wire-o. No incluye la impresión. | D68: Anillado metálico hasta 3/4 pulgada | H68: anillado, wire-o, wireo, espiral metalico, encuadernado con anillo metalico | I68: A4 o A3
A69: Encuadernación y terminaciones | B69: Armado de revistas | C69: Armado completo de revista o cuadernillo: plegado, refilado y 2 ganchos al centro. No incluye la impresión. | D69: Encuadernación abrochada | H69: armado de revistas, encuadernado a caballo, revista completa | I69: A4
A70: Encuadernación y terminaciones | B70: Encuadernación fresada | C70: Encuadernación pegada, tipo libro. No incluye la impresión. | D70: Encuadernación fresada | H70: encuadernación, empastado, tesis, libros | I70: A4
A71: Encuadernación y terminaciones | B71: Laminado A4 | C71: Plastificado fino sobre el impreso, mate o brillante. Se cobra por unidad. | D71: Laminado A4 | H71: laminado, plastificado, brillo, mate | I71: A4
A72: Encuadernación y terminaciones | B72: Plastificado de documentos A4 | C72: Plastificado rígido de documentos en A4. Se cobra por unidad. | D72: Plastificado A4 | H72: plastificado, laminado rígido, plastificar | I72: A4
A73: Encuadernación y terminaciones | B73: Plastificado de documentos oficio | C73: Plastificado rígido en tamaño oficio. | D73: Plastificado oficio | I73: oficio
A74: Encuadernación y terminaciones | B74: Plastificado de documentos A3 | C74: Plastificado rígido en A3. | D74: Plastificado A3 | I74: A3
A75: Encuadernación y terminaciones | B75: Plastificado de credencial o carnet 9x13 | C75: Plastificado de credenciales y carnets, 9x13 cm. | D75: Plastificado carnet | H75: credencial, carnet, plastificar carnet | I75: 9x13 cm
A76: Encuadernación y terminaciones | B76: Plastificado cocodrilo | C76: Plastificado cocodrilo, el formato más chico. | D76: Plastificado cocodrilo | H76: cocodrilo
A77: Encuadernación y terminaciones | B77: Puntillado | C77: Perforado para desprender a mano, sobre un impreso. Se usa en rifas y talonarios. Se cobra por pasada. | D77: Puntillado | H77: puntillado, perforado, linea de corte, rifas, talonarios, trazado troquelado manual de papel, pespunteado
A78: Encuadernación y terminaciones | B78: Colocación de ojalillos | C78: Colocación de ojalillos metálicos. Se cobra por ojalillo. | D78: Colocación de ojalillos | H78: ojales, ojalillos, arandelas
A79: Encuadernación y terminaciones | B79: Numerado correlativo | C79: Numeración correlativa sobre el impreso. | D79: Numerado correlativo | H79: numerado, numeración, correlativo
A80: Encuadernación y terminaciones | B80: 500 perforados o microperforados | C80: Perforado o microperforado. El precio es por los 500. | D80: Perforado x500 | H80: perforado, agujeros, microperforado
A81: Folletería y editorial | B81: 500 volantes A6 | C81: Volantes 10x15 cm full color. El precio es por los 500. | D81: Volantes A6 x500 | H81: volantes, flyers, panfletos, folletos | I81: A6 (10x15 cm)
A82: Folletería y editorial | B82: Libros de medicina | C82: Cuatro títulos puntuales: ROSS Histología, LANGMAN Embriología Médica, GUYTON & HALL Fisiología y MOORE Anatomía Clínica. Mismo precio cada uno, sin importar la cantidad de páginas. Solo estos cuatro. | D82: Libros de medicina | H82: ross, langman, guyton, hall, moore, histología, embriología, fisiología, anatomía, anatomía clínica
A83: Folletería y editorial | B83: Pack 4 libros de medicina | C83: Los cuatro libros juntos: ROSS, LANGMAN, GUYTON & HALL y MOORE. | D83: Pack 4 libros de medicina | H83: pack de libros, combo medicina, los 4 libros
A84: Folletería y editorial | B84: Anotadores personalizados | C84: Taco de anotador 10x15 cm impreso en negro. Se cobra por unidad. | D84: Anotadores personalizados en negro | H84: anotadores, tacos, blocks, libretas | I84: 10x15 cm
A85: Folletería y editorial | B85: Anotadores personalizados en color | C85: El mismo taco 10x15 cm, impreso full color. | D85: Anotadores personalizados en color | I85: 10x15 cm
A86: Gran formato y cartelería | B86: Posters A3 y A2 | C86: Poster impreso full color, A3 o A2. Se cobra por unidad. | D86: Posters A3 y A2 | H86: posters, afiches, láminas | I86: A3 o A2
A87: Gran formato y cartelería | B87: Banner roll-up 85x200 cm | C87: Banner enrollable con estructura de aluminio y bolso. Listo para usar. | D87: Banner roll-up | E87: 85 | F87: 200 | H87: roll up, banner enrollable
A88: Gran formato y cartelería | B88: Porta banner tipo X 90x190 cm | C88: Estructura tipo X con la lona impresa, 90x190 cm. Liviana y fácil de armar. | D88: Porta banner tipo X | E88: 90 | F88: 190 | H88: porta banner, araña, banner tipo x
A89: Señalética y punto de venta | B89: Cartelería de seguridad e higiene A3 | C89: Carteles reglamentarios de seguridad e higiene, en A3 (29,7x42 cm) sobre plástico corrugado. Este precio es solo para el A3; en otra medida se cotiza como cartel. | D89: Cartelería en plástico corrugado A3 | H89: cartel de seguridad, señalética, higiene y seguridad, cartel reglamentario | I89: A3
A90: Señalética y punto de venta | B90: Señalética de baños y accesos A3 | C90: Señalética de baños y accesos en A3 sobre plástico corrugado. Para interior también se puede en A4 plastificado. | D90: Cartelería en plástico corrugado A3 | H90: señalética, cartel de baño, cartel de acceso, señal | I90: A3
A91: Señalética y punto de venta | B91: Cartas y menús plastificados A4 | C91: Carta o menú A4 impreso y plastificado, para que aguante el uso diario. | D91: Cartas y menús plastificados | H91: cartas, menús, carta de restaurante | I91: A4
A92: Señalética y punto de venta | B92: Carteles de precios y ofertas A3 | C92: Cartel de precios u ofertas en A3: impresión color más plastificado. | D92: Impresión color más plastificado | H92: cartel de precios, cartel de oferta, cartel para el local | I92: A3
A93: Eventos y sociales | B93: 100 tarjetas de agradecimiento | C93: Tarjetas 9x5 cm para agradecer a los invitados. El precio es por las 100. | D93: Tarjetas 9x5 simple faz x100 | E93: 9 | F93: 5 | H93: tarjetas de agradecimiento, tarjetas de evento
A94: Carteles y vidrieras | B94: Vinilo microperforado para vidriera 1x1 m | C94: Vinilo microperforado para vidrieras: desde adentro se ve hacia afuera, desde afuera se ve la impresión. Se cotiza por metro cuadrado, mínimo medio m2. | D94: Vinilo microperforado | E94: 100 | F94: 100 | H94: microperforado, vinilo para vidriera, vinilo que se ve de adentro
A95: Carteles y vidrieras | B95: Cartel en PVC espumado 3 mm 50x70 cm | C95: Cartel en PVC espumado de 3 mm con vinilo brillo o mate. Más firme y durable que el plástico corrugado, que es la alternativa más económica. Se cotiza por metro cuadrado, mínimo medio m2. | D95: PVC espumado 3 mm con vinilo | E95: 50 | F95: 70 | H95: pvc, pvc espumado, cartel rigido, sintra, letrero
A96: Gran formato y cartelería | B96: Impresión de planos A1 | C96: Impresión de planos en papel obra 90 g, por metro cuadrado, mínimo medio m2. El precio depende de cuánta tinta cubre el dibujo: lineal (solo líneas), 25%, 50% o 100% de cobertura de color/relleno — decinos cuál para cotizar. | D96: Impresión de planos lineal | E96: 59.4 | F96: 84.1 | H96: planos, planos de obra, autocad, plotteo, ploteo de planos, plotter
A97: Diseño y servicios | B97: Escaneo de planos | C97: Escaneo y digitalización de planos en gran formato. Se cobra por metro lineal escaneado. También escaneamos A3. | D97: Escaneo de planos | H97: escanear, escaneo, digitalizar, escaneo de planos, pasar a digital | I97: A3
A98: Stickers con forma | B98: Plancha A4 de stickers | C98: Hoja A4 de stickers en papel autoadhesivo, con medio corte para despegarlos de a uno. Incluye la impresión y el corte. El precio baja bastante desde 2 planchas. | D98: Plancha A4 de stickers | H98: plancha de stickers, hoja de stickers, stickers en plancha, calcos en hoja | I98: A4
A99: Gran formato y cartelería | B99: Lona 1,9x0,9 m con porta banner 2 velas | C99: La lona impresa full color con bolsillos, más la estructura tipo araña de 2 velas. Se arma y se guarda en minutos. El precio incluye las dos cosas. | D99: Lona 1,9x0,9 m con porta banner 2 velas | H99: banner completo, kit de banner, lona con estructura, araña con lona, banner armado | I99: 1,9 x 0,9 m
A100: Gran formato y cartelería | B100: Lona 2x0,85 m con porta banner roll up | C100: La lona impresa full color más el roll up con estuche: la lona se enrolla dentro de la base. No lleva bolsillos. El precio incluye las dos cosas. | D100: Lona 2x0,85 m con porta banner roll up | H100: roll up, rollup con lona, banner enrollable, banner completo, kit de banner | I100: 2 x 0,85 m
A101: Encuadernación y terminaciones | B101: Troquelado (corte con forma) | C101: Corte con forma sobre un impreso ya listo, no incluye la impresión. Minimo 10 piezas ($10.000). Se cobra por pieza a partir de 11. | D101: Troquelado (corte con forma en papel) | H101: troquelado, corte con forma, troquel
A102: Impresión digital | B102: Corte a medida en Obra 80 gr | C102: Impresión y corte recto a la medida que pida el cliente, en Obra 80 gr. Lleva ademas un recargo FIJO de $5.000 por modelo de corte (material 'Corte a medida'), aparte del papel. | D102: Obra 80 gr | H102: corte a medida, cortado a medida, medida a pedido
A103: Impresión digital | B103: Corte a medida en Ilustracion brillo 150 gr | C103: Impresión y corte recto a la medida que pida el cliente, en Ilustracion brillo 150 gr. Lleva ademas un recargo FIJO de $5.000 por modelo de corte (material 'Corte a medida'), aparte del papel. | D103: Ilustracion brillo 150 gr | H103: corte a medida, cortado a medida, medida a pedido
A104: Impresión digital | B104: Corte a medida en Ilustracion mate 240 gr | C104: Impresión y corte recto a la medida que pida el cliente, en Ilustracion mate 240 gr. Lleva ademas un recargo FIJO de $5.000 por modelo de corte (material 'Corte a medida'), aparte del papel. | D104: Ilustracion mate 240 gr | H104: corte a medida, cortado a medida, medida a pedido
A105: Impresión digital | B105: Corte a medida en Ilustracion mate 300 gr | C105: Impresión y corte recto a la medida que pida el cliente, en Ilustracion mate 300 gr. Lleva ademas un recargo FIJO de $5.000 por modelo de corte (material 'Corte a medida'), aparte del papel. | D105: Ilustracion mate 300 gr | H105: corte a medida, cortado a medida, medida a pedido
A106: Impresión digital | B106: Corte a medida en Opalina 240 gr | C106: Impresión y corte recto a la medida que pida el cliente, en Opalina 240 gr. Lleva ademas un recargo FIJO de $5.000 por modelo de corte (material 'Corte a medida'), aparte del papel. | D106: Opalina 240 gr | H106: corte a medida, cortado a medida, medida a pedido
A107: Encuadernación y terminaciones | B107: Laminado A3 | C107: Plastificado fino sobre el impreso, mate o brillante, en A3. Se cobra por unidad. | D107: Laminado A3 | H107: laminado, plastificado, brillo, mate | I107: A3
A108: Encuadernación y terminaciones | B108: Laminado por metro | C108: Plastificado fino sobre el impreso, mate o brillante, para piezas grandes. Se cobra por metro lineal. | D108: Laminado metro lineal | H108: laminado, plastificado, brillo, mate
A109: Encuadernación y terminaciones | B109: Encapsulado A4 | C109: Plastificado grueso de ambos lados sobre el impreso, en A4. Mas resistente que el laminado. Se cobra por unidad. | D109: Encapsulado A4 | H109: encapsulado, plastificado grueso | I109: A4
A110: Encuadernación y terminaciones | B110: Encapsulado A3 | C110: Plastificado grueso de ambos lados sobre el impreso, en A3. Se cobra por unidad. | D110: Encapsulado A3 | H110: encapsulado, plastificado grueso | I110: A3
A111: Encuadernación y terminaciones | B111: Encapsulado por metro | C111: Plastificado grueso de ambos lados, para piezas grandes. Se cobra por metro lineal. | D111: Encapsulado metro lineal | H111: encapsulado, plastificado grueso
A112: Encuadernación y terminaciones | B112: Anillado metálico 1 pulgada | C112: Anillado con espiral metalico wire-o, grosor 1 pulgada. No incluye la impresión. | D112: Anillado metálico 1 pulgada | H112: anillado, wire-o, wireo, espiral metalico | I112: A4 o A3
A113: Encuadernación y terminaciones | B113: Anillado metálico 1 1/8 pulgada | C113: Anillado con espiral metalico wire-o, grosor 1 1/8 pulgada. No incluye la impresión. | D113: Anillado metálico 1 1/8 pulgada | H113: anillado, wire-o, wireo, espiral metalico | I113: A4 o A3
A114: Encuadernación y terminaciones | B114: Anillado metálico 1 1/4 pulgada | C114: Anillado con espiral metalico wire-o, grosor 1 1/4 pulgada. No incluye la impresión. | D114: Anillado metálico 1 1/4 pulgada | H114: anillado, wire-o, wireo, espiral metalico | I114: A4 o A3
A115: Encuadernación y terminaciones | B115: Anillado metálico 1 1/2 pulgada | C115: Anillado con espiral metalico wire-o, grosor 1 1/2 pulgada. No incluye la impresión. | D115: Anillado metálico 1 1/2 pulgada | H115: anillado, wire-o, wireo, espiral metalico | I115: A4 o A3
A116: Encuadernación y terminaciones | B116: Anillado plástico A3 | C116: Anillado con espiral plástico en A3. Se cobra por unidad y no incluye la impresión. | D116: Anillado plástico A3 | H116: anillado, espiralado, espiral, encuadernado con anillo | I116: A3
A117: Impresión digital | B117: Impresión color A4 106gr | C117: Impresión full color en papel obra 106 gr (mas grueso que el estandar), de un lado. Se cobra por hoja y el precio baja por cantidad. | D117: Impresión color A4 106gr simple faz | H117: imprimir, impresiones, copias en color, papel grueso, obra 106 | I117: A4
A118: Impresión digital | B118: Impresión color A4 106gr doble faz | C118: Full color de los dos lados de la hoja, en papel obra 106 gr. | D118: Impresión color A4 106gr doble faz | H118: papel grueso, obra 106 | I118: A4
...

Sheet Materiales
A1: Material | B1: Unidad | C1: Desde | D1: Hasta | E1: Precio por unidad | F1: Mínimo facturable | G1: Nota | H1: Área útil ancho (cm) | I1: Área útil alto (cm) | J1: Separación (cm) | K1: Sin mínimo por trabajo | L1: Familia | M1: Piezas por paquete
A2: Papel autoadhesivo troquelado o medio corte | B2: pliego A3 | C2: 1 | D2: 1 | E2: 2500 | H2: 28 | I2: 44 | J2: 0.3
A3: Papel autoadhesivo troquelado o medio corte | B3: pliego A3 | C3: 2 | D3: 10 | E3: 2200
A4: Papel autoadhesivo troquelado o medio corte | B4: pliego A3 | C4: 11 | D4: 50 | E4: 2000
A5: Papel autoadhesivo troquelado o medio corte | B5: pliego A3 | C5: 51 | D5: 100 | E5: 1900
A6: Papel autoadhesivo troquelado o medio corte | B6: pliego A3 | C6: 101 | E6: 1710
A7: Papel autoadhesivo solo impresión | B7: pliego A3 | C7: 1 | D7: 100 | E7: 1800 | H7: 31 | I7: 46 | J7: 0
A8: Papel autoadhesivo solo impresión | B8: pliego A3 | C8: 101 | E8: 1620
A9: OPP brillo | B9: pliego A3 | C9: 1 | D9: 9 | E9: 2400 | H9: 31 | I9: 46 | J9: 0
A10: OPP brillo | B10: pliego A3 | C10: 10 | D10: 29 | E10: 2160
A11: OPP brillo | B11: pliego A3 | C11: 30 | E11: 1920
A12: OPP brillo troquelado | B12: pliego A3 | C12: 1 | D12: 9 | E12: 2800 | H12: 28 | I12: 44 | J12: 0.3
A13: OPP brillo troquelado | B13: pliego A3 | C13: 10 | D13: 29 | E13: 2520
A14: OPP brillo troquelado | B14: pliego A3 | C14: 30 | E14: 2240
A15: OPP plata, holográfico, cristal o mate | B15: pliego A3 | C15: 1 | D15: 9 | E15: 2600 | H15: 31 | I15: 46 | J15: 0
A16: OPP plata, holográfico, cristal o mate | B16: pliego A3 | C16: 10 | D16: 29 | E16: 2340
A17: OPP plata, holográfico, cristal o mate | B17: pliego A3 | C17: 30 | E17: 2080
A18: OPP plata, holográfico, cristal o mate troquelado | B18: pliego A3 | C18: 1 | D18: 9 | E18: 3000 | H18: 28 | I18: 44 | J18: 0.3
A19: OPP plata, holográfico, cristal o mate troquelado | B19: pliego A3 | C19: 10 | D19: 29 | E19: 2700
A20: OPP plata, holográfico, cristal o mate troquelado | B20: pliego A3 | C20: 30 | E20: 2400
A21: Lona | B21: m2 | C21: 1 | E21: 16000 | F21: 0.5
A22: Vinilo y lona UV | B22: m2 | C22: 1 | E22: 22000 | F22: 0.5
A23: Vinilo y lona UV con blanco o barniz | B23: m2 | C23: 1 | E23: 26000 | F23: 0.5
A24: Vinilo UV montado en corrugado | B24: m2 | C24: 1 | E24: 30000 | F24: 0.5
A25: Vinilo UV troquelado | B25: m2 | C25: 1 | E25: 28000 | F25: 0.5
A26: Tarjetas 9x5 simple faz x100 | B26: paquete de 100 tarjetas | C26: 1 | E26: 13200 | L26: Tarjetas 9x5 simple faz
A27: Tarjetas 9x5 simple faz encapsuladas x100 | B27: paquete de 100 tarjetas | C27: 1 | E27: 16500 | L27: Tarjetas 9x5 simple faz encapsuladas
A28: Tarjetas 9x5 doble faz x100 | B28: paquete de 100 tarjetas | C28: 1 | E28: 16500 | L28: Tarjetas 9x5 doble faz
A29: Tarjetas 9x5 doble faz encapsuladas x100 | B29: paquete de 100 tarjetas | C29: 1 | E29: 18700 | L29: Tarjetas 9x5 doble faz encapsuladas
A30: Tarjetas 9x5 kraft simple faz x100 | B30: paquete de 100 tarjetas | C30: 1 | E30: 17600 | L30: Tarjetas 9x5 kraft simple faz
A31: Tarjetas 9x5 kraft doble faz x100 | B31: paquete de 100 tarjetas | C31: 1 | E31: 24200 | L31: Tarjetas 9x5 kraft doble faz
A32: Tarjetas 9x5 simple faz x500 | B32: paquete de 500 tarjetas | C32: 1 | E32: 28000 | L32: Tarjetas 9x5 simple faz
A33: Tarjetas 9x5 simple faz encapsuladas x500 | B33: paquete de 500 tarjetas | C33: 1 | E33: 38000 | L33: Tarjetas 9x5 simple faz encapsuladas
A34: Tarjetas 9x5 doble faz x500 | B34: paquete de 500 tarjetas | C34: 1 | E34: 38000 | L34: Tarjetas 9x5 doble faz
A35: Tarjetas 9x5 doble faz encapsuladas x500 | B35: paquete de 500 tarjetas | C35: 1 | E35: 45000 | L35: Tarjetas 9x5 doble faz encapsuladas
A36: Tarjetas 9x5 simple faz x1000 | B36: paquete de 1000 tarjetas | C36: 1 | E36: 42000 | L36: Tarjetas 9x5 simple faz
A37: Tarjetas 9x5 simple faz encapsuladas x1000 | B37: paquete de 1000 tarjetas | C37: 1 | E37: 54000 | L37: Tarjetas 9x5 simple faz encapsuladas
... A39: Tarjetas 9x5 doble faz encapsuladas x1000 | B39: paquete de 1000 tarjetas | C39: 1 | E39: 59000 | L39: Tarjetas 9x5 doble faz encapsuladas
A40: Hojas membretadas A4 x500 | B40: paquete de 500 hojas | C40: 1 | E40: 35000
A41: Sobres impresos x100 | B41: paquete de 100 sobres | C41: 1 | E41: 25000
A42: Talonarios x10 | B42: paquete de 10 talonarios | C42: 1 | E42: 54000
A43: Sobres oficio inglés | B43: unidad | C43: 1 | D43: 200 | E43: 250 | K43: sí
A44: Sobres oficio inglés | B44: unidad | C44: 201 | D44: 500 | E44: 220
A45: Sobres oficio inglés | B45: unidad | C45: 501 | D45: 1000 | E45: 190
A46: Sobres oficio inglés | B46: unidad | C46: 1001 | E46: 180
A47: Carpetas institucionales sin laminar | B47: unidad | C47: 1 | D47: 20 | E47: 2600 | K47: sí
A48: Carpetas institucionales sin laminar | B48: unidad | C48: 21 | D48: 50 | E48: 2500
A49: Carpetas institucionales sin laminar | B49: unidad | C49: 51 | D49: 100 | E49: 2300
A50: Carpetas institucionales sin laminar | B50: unidad | C50: 101 | D50: 300 | E50: 2100
A51: Carpetas institucionales sin laminar | B51: unidad | C51: 301 | E51: 1900
A52: Carpetas institucionales laminadas | B52: unidad | C52: 1 | D52: 20 | E52: 3000 | K52: sí
A53: Carpetas institucionales laminadas | B53: unidad | C53: 21 | D53: 50 | E53: 2800
A54: Carpetas institucionales laminadas | B54: unidad | C54: 51 | D54: 100 | E54: 2600
A55: Carpetas institucionales laminadas | B55: unidad | C55: 101 | D55: 300 | E55: 2400
A56: Carpetas institucionales laminadas | B56: unidad | C56: 301 | E56: 2300
A57: Recetarios en negro | B57: unidad | C57: 1 | D57: 10 | E57: 4000 | K57: sí
A58: Recetarios en negro | B58: unidad | C58: 11 | D58: 20 | E58: 3400
A59: Recetarios en negro | B59: unidad | C59: 21 | D59: 50 | E59: 3000
A60: Recetarios en negro | B60: unidad | C60: 51 | E60: 2600
A61: Recetarios en color | B61: unidad | C61: 1 | D61: 10 | E61: 4500 | K61: sí
A62: Recetarios en color | B62: unidad | C62: 11 | D62: 20 | E62: 3800
A63: Recetarios en color | B63: unidad | C63: 21 | D63: 50 | E63: 3200
A64: Recetarios en color | B64: unidad | C64: 51 | E64: 2800
A65: Impresión color A4 simple faz | B65: hoja | C65: 1 | D65: 70 | E65: 400 | K65: sí
A66: Impresión color A4 simple faz | B66: hoja | C66: 71 | D66: 150 | E66: 150
A67: Impresión color A4 simple faz | B67: hoja | C67: 151 | D67: 500 | E67: 80
A68: Impresión color A4 simple faz | B68: hoja | C68: 501 | E68: 70
A69: Impresión color A4 doble faz | B69: hoja | C69: 1 | D69: 70 | E69: 600 | K69: sí
A70: Impresión color A4 doble faz | B70: hoja | C70: 71 | D70: 150 | E70: 200
A71: Impresión color A4 doble faz | B71: hoja | C71: 151 | D71: 500 | E71: 120
A72: Impresión color A4 doble faz | B72: hoja | C72: 501 | E72: 110
A73: Impresión blanco y negro A4 simple faz | B73: hoja | C73: 1 | D73: 10 | E73: 100 | K73: sí
A74: Impresión blanco y negro A4 simple faz | B74: hoja | C74: 11 | E74: 70
A75: Impresión blanco y negro A4 doble faz | B75: hoja | C75: 1 | D75: 10 | E75: 150 | K75: sí
A76: Impresión blanco y negro A4 doble faz | B76: hoja | C76: 11 | D76: 100 | E76: 96
A77: Impresión blanco y negro A4 doble faz | B77: hoja | C77: 101 | D77: 500 | E77: 88
A78: Impresión blanco y negro A4 doble faz | B78: hoja | C78: 501 | D78: 1000 | E78: 86
A79: Impresión blanco y negro A4 doble faz | B79: hoja | C79: 1001 | E79: 84
A80: Impresión color A3 | B80: hoja | C80: 1 | E80: 1200 | K80: sí
A81: Impresión blanco y negro A3 | B81: hoja | C81: 1 | E81: 600 | K81: sí
A82: Impresión en papel ilustración | B82: hoja | C82: 1 | E82: 800 | K82: sí
A83: Impresión en opalina | B83: hoja | C83: 1 | E83: 900 | K83: sí
A84: Anillado plástico A4/Oficio | B84: unidad | C84: 1 | E84: 2400 | K84: sí | L84: Anillado plástico
A85: Anillado metálico hasta 3/4 pulgada | B85: unidad | C85: 1 | E85: 3200 | K85: sí | L85: Anillado metálico
A86: Encuadernación abrochada | B86: unidad | C86: 1 | E86: 2000 | K86: sí
A87: Encuadernación fresada | B87: unidad | C87: 1 | D87: 1 | E87: 7000
A88: Encuadernación fresada | B88: unidad | C88: 2 | D88: 10 | E88: 5000
A89: Laminado A4 | B89: unidad | C89: 1 | E89: 330 | K89: sí | L89: Laminado
A90: Plastificado A4 | B90: unidad | C90: 1 | E90: 2200 | K90: sí | L90: Plastificado de documentos
A91: Plastificado oficio | B91: unidad | C91: 1 | E91: 2400 | K91: sí | L91: Plastificado de documentos
A92: Plastificado A3 | B92: unidad | C92: 1 | E92: 3000 | K92: sí | L92: Plastificado de documentos
A93: Plastificado carnet | B93: unidad | C93: 1 | E93: 1500 | K93: sí | L93: Plastificado de documentos
A94: Plastificado cocodrilo | B94: unidad | C94: 1 | E94: 800 | K94: sí | L94: Plastificado de documentos
A95: Puntillado | B95: pasada | C95: 1 | E95: 50 | G95: Perforado para desprender (rifas, talonarios). No es troquelado ni corte a medida. | K95: sí
A96: Colocación de ojalillos | B96: unidad | C96: 1 | E96: 1000 | K96: sí
A97: Numerado correlativo | B97: unidad | C97: 1 | E97: 5000
A98: Perforado x500 | B98: paquete de 500 perforados | C98: 1 | E98: 4000
A99: Volantes A6 x500 | B99: paquete de 500 volantes | C99: 1 | E99: 12000
A100: Libros de medicina | B100: unidad | C100: 1 | E100: 30000
A101: Pack 4 libros de medicina | B101: pack | C101: 1 | E101: 99000
...

Sheet Pendientes
A1: Producto | B1: Descripción | C1: Cómo se cobra | D1: Notas

Sheet _listas
A1: Materiales — desplegable de Productos | B1: Colecciones — desplegable de Productos
A2: {=IFERROR(INDEX(Materiales!$A$2:$A$300,MATCH(0,COUNTIF($A$1:A1,Materiales!$A$2:$A$300)+IF(Materiales!$A$2:$A$300="",1,0),0)),"")} | B2: {=IFERROR(INDEX(Colecciones!$A$2:$A$300,MATCH(0,COUNTIF($B$1:B1,Colecciones!$A$2:$A$300)+IF(Colecciones!$A$2:$A$300="",1,0),0)),"")}
A3: {=IFERROR(INDEX(Materiales!$A$2:$A$300,MATCH(0,COUNTIF($A$1:A2,Materiales!$A$2:$A$300)+IF(Materiales!$A$2:$A$300="",1,0),0)),"")} | B3: {=IFERROR(INDEX(Colecciones!$A$2:$A$300,MATCH(0,COUNTIF($B$1:B2,Colecciones!$A$2:$A$300)+IF(Colecciones!$A$2:$A$300="",1,0),0)),"")}
A4: {=IFERROR(INDEX(Materiales!$A$2:$A$300,MATCH(0,COUNTIF($A$1:A3,Materiales!$A$2:$A$300)+IF(Materiales!$A$2:$A$300="",1,0),0)),"")} | B4: {=IFERROR(INDEX(Colecciones!$A$2:$A$300,MATCH(0,COUNTIF($B$1:B3,Colecciones!$A$2:$A$300)+IF(Colecciones!$A$2:$A$300="",1,0),0)),"")}
A5: {=IFERROR(INDEX(Materiales!$A$2:$A$300,MATCH(0,COUNTIF($A$1:A4,Materiales!$A$2:$A$300)+IF(Materiales!$A$2:$A$300="",1,0),0)),"")} | B5: {=IFERROR(INDEX(Colecciones!$A$2:$A$300,MATCH(0,COUNTIF($B$1:B4,Colecciones!$A$2:$A$300)+IF(Colecciones!$A$2:$A$300="",1,0),0)),"")}
A6: {=IFERROR(INDEX(Materiales!$A$2:$A$300,MATCH(0,COUNTIF($A$1:A5,Materiales!$A$2:$A$300)+IF(Materiales!$A$2:$A$300="",1,0),0)),"")} | B6: {=IFERROR(INDEX(Colecciones!$A$2:$A$300,MATCH(0,COUNTIF($B$1:B5,Colecciones!$A$2:$A$300)+IF(Colecciones!$A$2:$A$300="",1,0),0)),"")}
A7: {=IFERROR(INDEX(Materiales!$A$2:$A$300,MATCH(0,COUNTIF($A$1:A6,Materiales!$A$2:$A$300)+IF(Materiales!$A$2:$A$300="",1,0),0)),"")} | B7: {=IFERROR(INDEX(Colecciones!$A$2:$A$300,MATCH(0,COUNTIF($B$1:B6,Colecciones!$A$2:$A$300)+IF(Colecciones!$A$2:$A$300="",1,0),0)),"")}
A8: {=IFERROR(INDEX(Materiales!$A$2:$A$300,MATCH(0,COUNTIF($A$1:A7,Materiales!$A$2:$A$300)+IF(Materiales!$A$2:$A$300="",1,0),0)),"")} | B8: {=IFERROR(INDEX(Colecciones!$A$2:$A$300,MATCH(0,COUNTIF($B$1:B7,Colecciones!$A$2:$A$300)+IF(Colecciones!$A$2:$A$300="",1,0),0)),"")}
A9: {=IFERROR(INDEX(Materiales!$A$2:$A$300,MATCH(0,COUNTIF($A$1:A8,Materiales!$A$2:$A$300)+IF(Materiales!$A$2:$A$300="",1,0),0)),"")} | B9: {=IFERROR(INDEX(Colecciones!$A$2:$A$300,MATCH(0,COUNTIF($B$1:B8,Colecciones!$A$2:$A$300)+IF(Colecciones!$A$2:$A$300="",1,0),0)),"")}
A10: {=IFERROR(INDEX(Materiales!$A$2:$A$300,MATCH(0,COUNTIF($A$1:A9,Materiales!$A$2:$A$300)+IF(Materiales!$A$2:$A$300="",1,0),0)),"")} | B10: {=IFERROR(INDEX(Colecciones!$A$2:$A$300,MATCH(0,COUNTIF($B$1:B9,Colecciones!$A$2:$A$300)+IF(Colecciones!$A$2:$A$300="",1,0),0)),"")}
A11: {=IFERROR(INDEX(Materiales!$A$2:$A$300,MATCH(0,COUNTIF($A$1:A10,Materiales!$A$2:$A$300)+IF(Materiales!$A$2:$A$300="",1,0),0)),"")} | B11: {=IFERROR(INDEX(Colecciones!$A$2:$A$300,MATCH(0,COUNTIF($B$1:B10,Colecciones!$A$2:$A$300)+IF(Colecciones!$A$2:$A$300="",1,0),0)),"")}
A12: {=IFERROR(INDEX(Materiales!$A$2:$A$300,MATCH(0,COUNTIF($A$1:A11,Materiales!$A$2:$A$300)+IF(Materiales!$A$2:$A$300="",1,0),0)),"")} | B12: {=IFERROR(INDEX(Colecciones!$A$2:$A$300,MATCH(0,COUNTIF($B$1:B11,Colecciones!$A$2:$A$300)+IF(Colecciones!$A$2:$A$300="",1,0),0)),"")}
A13: {=IFERROR(INDEX(Materiales!$A$2:$A$300,MATCH(0,COUNTIF($A$1:A12,Materiales!$A$2:$A$300)+IF(Materiales!$A$2:$A$300="",1,0),0)),"")} | B13: {=IFERROR(INDEX(Colecciones!$A$2:$A$300,MATCH(0,COUNTIF($B$1:B12,Colecciones!$A$2:$A$300)+IF(Colecciones!$A$2:$A$300="",1,0),0)),"")}
... A300: {=IFERROR(INDEX(Materiales!$A$2:$A$300,MATCH(0,COUNTIF($A$1:A299,Materiales!$A$2:$A$300)+IF(Materiales!$A$2:$A$300="",1,0),0)),"")} | B300: {=IFERROR(INDEX(Colecciones!$A$2:$A$300,MATCH(0,COUNTIF($B$1:B299,Colecciones!$A$2:$A$300)+IF(Colecciones!$A$2:$A$300="",1,0),0)),"")}
