Workbook

Sheet Instrucciones
A1: CÓMO USAR ESTE ARCHIVO
A2: Este archivo NO tiene precios cerrados por cantidad. Tiene el framework para calcular cualquier cantidad.
A3: Cada producto dice de qué material se hace. Las medidas del catálogo son REFERENCIAS: se cotiza CUALQUIER medida que pida el cliente.
A4: La primera parte explica cómo COTIZAR (leer). La segunda, cómo CARGAR cosas nuevas (escribir).
A6: ═══ PARTE 1: CÓMO COTIZAR ═══
A7: MODO "pliego" (stickers y etiquetas en papel autoadhesivo u OPP)
A9: 1. Rinde: cuántas piezas entran en una unidad de cobro. Se calcula con la geometría del
A12: MATERIAL (hoja Materiales: 'Área útil ancho/alto (cm)' y 'Separación (cm)'):
A13: columnas × filas que entran = floor((útil + sep) ÷ (pieza + sep)) en cada eje,
A14: probando las DOS orientaciones y tomando la que rinde más. Vale CUALQUIER medida.
A15: Ejemplo: pieza de 12x8 troquelada (área útil 28x44, separación 0,3).
A16: Acostada: 28,3÷12,3 = 2 columnas × 44,3÷8,3 = 5 filas = 10. Parada: 3 × 3 = 9. → 10.
... A150: Los cambios NO llegan al bot hasta que se ingesta desde ahí.

Sheet Colecciones
A1: Colección | B1: Descripción | C1: Material base | D1: Sin mínimo por trabajo
A2: Stickers con forma | B2: Stickers y etiquetas cortados con forma, para uso en interior. Se imprimen en papel autoadhesivo brillo o en OPP (más resistente al roce y a la humedad, y disponible en holográfico, plata, cristal y mate). Se entregan troquelados sueltos o en plancha con medio corte, al mismo precio. Se cotizan por pliego A3. | C2: Papel autoadhesivo troquelado o medio corte
A3: Stickers para exterior | B3: Stickers y etiquetas cortados con forma, impresos en vinilo con tinta UV, que aguanta sol, lluvia y lavado. Para autos, cascos, heladeras, obradores y todo lo que quede a la intemperie. Se cotizan por metro cuadrado. | C3: Vinilo UV troquelado
A4: Carteles y vidrieras | B4: Impresión de gran formato para pared, vidrio o chapa. Adhesivos, que se pegan directo sobre la superficie, o rígidos, montados sobre plástico corrugado para que se sostengan solos. Para vidrieras hay además opciones de microperforado y esmerilado. Se cotizan por metro cuadrado. | C4: Vinilo y lona UV
A5: Banners y lonas | B5: Lona impresa full color con dobladillo y ojalillos, lista para colgar. Para el frente del local, eventos, ferias y publicidad en vía pública. Se cotizan por metro cuadrado. | C5: Lona
A6: Tarjetas personales | B6: Tarjetas de presentación 9x5 cm, full color. Simple o doble faz, en papel ilustración o kraft 280 g, con opción encapsulada (plastificada de ambos lados). Se cotizan por cantidad cerrada: 100, 500 o 1000. | C6: Tarjetas 9x5 simple faz x100
A7: Papelería comercial | B7: Papelería impresa con la marca del negocio: hojas membretadas, sobres, talonarios de factura o remito, notas de pedido, recetarios y carpetas institucionales.
A8: Impresión digital | B8: Impresión de archivos por hoja, en color o blanco y negro, A4 y A3. En papel obra, ilustración u opalina. El precio por hoja baja según la cantidad. | D8: sí
A9: Encuadernación y terminaciones | B9: Trabajos que se hacen sobre un impreso ya listo: anillado, wire-o, fresado, abrochado, laminado, plastificado, troquelado, ojalillos y numerado. Se cobran por unidad y no incluyen la impresión. | D9: sí
A10: Folletería y editorial | B10: Volantes, anotadores, apuntes y libros de estudio.
A11: Gran formato y cartelería | B11: Impresión de gran formato lista para usar: posters, porta banners tipo X y roll-up, y planos. También hay combos que traen la lona impresa junto con su estructura, a precio cerrado.
A12: Señalética y punto de venta | B12: Carteles de seguridad e higiene, cartas y menús plastificados, y carteles de precios para el local.
A13: Eventos y sociales | B13: Tarjetería para eventos: agradecimiento, invitaciones y afines.
A14: Diseño y servicios | B14: Servicios sobre archivos, sin impresión: escaneo y digitalización de planos y documentos en gran formato.
A15: Merchandising | B15: Imanes personalizados para heladera y promoción. Los chicos se cobran por unidad y bajan de precio por cantidad; los troquelados a medida se cotizan por metro cuadrado, mínimo medio m2. | C15: Iman impresión laminada y corte

Sheet Productos
A1: Colección | B1: Producto | C1: Descripción | D1: Material | E1: Ancho (cm) | F1: Alto (cm) | G1: Sinónimos | H1: Formato
A2: Stickers con forma | B2: Stickers 3x3 cm | C2: Los más chicos. Papel autoadhesivo brillo. Troquelados sueltos o en plancha con medio corte, mismo precio. | D2: Papel autoadhesivo troquelado o medio corte | E2: 3 | F2: 3
A3: Stickers con forma | B3: Etiquetas para frascos 6x3 cm | C3: Formato alargado para frascos y botellas chicas. Papel autoadhesivo brillo. | D3: Papel autoadhesivo troquelado o medio corte | E3: 6 | F3: 3
A4: Stickers con forma | B4: Stickers 5x5 cm | C4: Impresión full color, corte con forma. Papel autoadhesivo brillo. Troquelados sueltos o en plancha con medio corte. | D4: Papel autoadhesivo troquelado o medio corte | E4: 5 | F4: 5
A5: Stickers con forma | B5: Stickers en OPP brillo 5x5 cm | C5: OPP brillo: más resistente al roce y a la humedad que el papel. | D5: OPP brillo troquelado | E5: 5 | F5: 5
A6: Stickers con forma | B6: Stickers holográficos 5x5 cm | C6: OPP tornasolado. También en plata, cristal y mate, al mismo precio. | D6: OPP plata, holográfico, cristal o mate troquelado | E6: 5 | F6: 5
A7: Stickers con forma | B7: Etiquetas 9x5 cm | C7: Tamaño tarjeta. Papel autoadhesivo brillo, full color. | D7: Papel autoadhesivo troquelado o medio corte | E7: 9 | F7: 5
A8: Stickers con forma | B8: Etiquetas en OPP brillo 9x5 cm | C8: Tamaño tarjeta en OPP brillo. | D8: OPP brillo troquelado | E8: 9 | F8: 5
A9: Stickers con forma | B9: Stickers 7x7 cm | C9: Impresión full color, corte con forma. Papel autoadhesivo brillo. | D9: Papel autoadhesivo troquelado o medio corte | E9: 7 | F9: 7
A10: Stickers con forma | B10: Stickers en OPP brillo 7x7 cm | C10: OPP brillo: más resistente al roce y a la humedad que el papel. | D10: OPP brillo troquelado | E10: 7 | F10: 7
A11: Stickers con forma | B11: Stickers holográficos 7x7 cm | C11: OPP tornasolado. También en plata, cristal y mate, al mismo precio. | D11: OPP plata, holográfico, cristal o mate troquelado | E11: 7 | F11: 7
A12: Stickers con forma | B12: Stickers 10x10 cm | C12: Impresión full color, corte con forma. Papel autoadhesivo brillo. | D12: Papel autoadhesivo troquelado o medio corte | E12: 10 | F12: 10
A13: Stickers con forma | B13: Stickers en OPP brillo 10x10 cm | C13: OPP brillo: más resistente al roce y a la humedad que el papel. | D13: OPP brillo troquelado | E13: 10 | F13: 10
... A32: Banners y lonas | B32: Banner de lona 4x1 m | C32: Lona impresa full color con dobladillo y ojalillos. | D32: Lona | E32: 400 | F32: 100
A33: Stickers con forma | B33: Stickers en plancha sin cortar | C33: La plancha impresa sin corte: el cliente recorta a mano. Papel autoadhesivo brillo. Sale más barato que el troquelado. | D33: Papel autoadhesivo solo impresión | E33: 5 | F33: 5 | G33: sin cortar, sin troquelar, plancha entera, solo impresión, recorto yo
A34: Stickers con forma | B34: Stickers en OPP brillo sin cortar | C34: Plancha de OPP brillo impresa sin corte. Más resistente al roce y a la humedad que el papel. | D34: OPP brillo | E34: 5 | F34: 5
A35: Stickers con forma | B35: Stickers holográficos sin cortar | C35: Plancha de OPP tornasolado impresa sin corte. También en plata, cristal y mate. | D35: OPP plata, holográfico, cristal o mate | E35: 5 | F35: 5
A36: Carteles y vidrieras | B36: Cartel adhesivo con blanco o barniz | C36: Vinilo UV con una capa de blanco o barniz: da más cuerpo al color sobre superficies oscuras o transparentes. | D36: Vinilo y lona UV con blanco o barniz | E36: 50 | F36: 70 | G36: con blanco, con barniz, para vidrio, para superficie oscura
A37: Tarjetas personales | B37: 100 tarjetas 9x5 cm simple faz | C37: Tarjetas de presentación full color, impresas de un lado. El precio es por las 100. | D37: Tarjetas 9x5 simple faz x100 | E37: 9 | F37: 5 | G37: tarjetas personales, tarjetas de presentación, tarjetas comerciales
A38: Tarjetas personales | B38: 100 tarjetas 9x5 cm simple faz encapsuladas | C38: Impresas de un lado y plastificadas de los dos: más resistentes y con mejor tacto. | D38: Tarjetas 9x5 simple faz encapsuladas x100 | E38: 9 | F38: 5
A39: Tarjetas personales | B39: 100 tarjetas 9x5 cm doble faz | C39: Full color de los dos lados. El precio es por las 100. | D39: Tarjetas 9x5 doble faz x100 | E39: 9 | F39: 5
A40: Tarjetas personales | B40: 100 tarjetas 9x5 cm doble faz encapsuladas | C40: Impresas de los dos lados y plastificadas. | D40: Tarjetas 9x5 doble faz encapsuladas x100 | E40: 9 | F40: 5
A41: Tarjetas personales | B41: 100 tarjetas 9x5 cm en papel kraft simple faz | C41: Papel kraft 280 g, con textura y color natural. Impresas de un lado. | D41: Tarjetas 9x5 kraft simple faz x100 | E41: 9 | F41: 5
A42: Tarjetas personales | B42: 100 tarjetas 9x5 cm en papel kraft doble faz | C42: Papel kraft 280 g, impresas de los dos lados. | D42: Tarjetas 9x5 kraft doble faz x100 | E42: 9 | F42: 5
A43: Tarjetas personales | B43: 500 tarjetas 9x5 cm simple faz | C43: Full color de un lado. El precio es por las 500. | D43: Tarjetas 9x5 simple faz x500 | E43: 9 | F43: 5
A44: Tarjetas personales | B44: 500 tarjetas 9x5 cm simple faz encapsuladas | C44: De un lado y plastificadas. El precio es por las 500. | D44: Tarjetas 9x5 simple faz encapsuladas x500 | E44: 9 | F44: 5
A45: Tarjetas personales | B45: 500 tarjetas 9x5 cm doble faz | C45: Full color de los dos lados. El precio es por las 500. | D45: Tarjetas 9x5 doble faz x500 | E45: 9 | F45: 5
A46: Tarjetas personales | B46: 500 tarjetas 9x5 cm doble faz encapsuladas | C46: De los dos lados y plastificadas. El precio es por las 500. | D46: Tarjetas 9x5 doble faz encapsuladas x500 | E46: 9 | F46: 5
A47: Tarjetas personales | B47: 1000 tarjetas 9x5 cm simple faz | C47: Full color de un lado. El precio es por las 1000. | D47: Tarjetas 9x5 simple faz x1000 | E47: 9 | F47: 5
A48: Tarjetas personales | B48: 1000 tarjetas 9x5 cm simple faz encapsuladas | C48: De un lado y plastificadas. El precio es por las 1000. | D48: Tarjetas 9x5 simple faz encapsuladas x1000 | E48: 9 | F48: 5
A49: Tarjetas personales | B49: 1000 tarjetas 9x5 cm doble faz | C49: Full color de los dos lados. El precio es por las 1000. | D49: Tarjetas 9x5 doble faz x1000 | E49: 9 | F49: 5
A50: Tarjetas personales | B50: 1000 tarjetas 9x5 cm doble faz encapsuladas | C50: De los dos lados y plastificadas. El precio es por las 1000. | D50: Tarjetas 9x5 doble faz encapsuladas x1000 | E50: 9 | F50: 5
A51: Papelería comercial | B51: 500 hojas membretadas A4 | C51: Hojas A4 impresas con el logo y los datos del negocio. El precio es por las 500. | D51: Hojas membretadas A4 x500 | G51: hojas membretadas, papel con logo, membrete | H51: A4
A52: Papelería comercial | B52: 100 sobres impresos | C52: Sobres con el logo y los datos del negocio. El precio es por los 100. | D52: Sobres impresos x100 | E52: 21 | F52: 11 | G52: sobres membretados, sobres con logo
A53: Papelería comercial | B53: 10 talonarios de factura o remito | C53: 10 talonarios A5 de 50 juegos por duplicado, abrochados y troquelados. El precio es por los 10 talonarios. | D53: Talonarios x10 | G53: talonarios, facturas, remitos, notas de pedido, comandas | H53: A5
A54: Papelería comercial | B54: Sobres oficio inglés | C54: Sobre tamaño oficio inglés impreso. Se cobra por unidad y el precio baja por cantidad. | D54: Sobres oficio inglés | E54: 23.5 | F54: 12 | G54: sobres, sobres oficio
A55: Papelería comercial | B55: Carpetas institucionales | C55: Carpeta de presentación A4 cerrada, en cartulina 300 g, troquelada, con solapa y ranura. Sin laminar. Se cobra por unidad. | D55: Carpetas institucionales sin laminar | G55: carpetas, carpetas de presentación, folders | H55: A4 cerrada
A56: Papelería comercial | B56: Carpetas institucionales laminadas | C56: La misma carpeta A4, plastificada: más resistente al uso y al roce. | D56: Carpetas institucionales laminadas | H56: A4 cerrada
A57: Papelería comercial | B57: Recetarios en negro | C57: Talonario de recetas impreso en negro. Mínimo 5 unidades. | D57: Recetarios en negro | G57: recetarios, recetas médicas, blocks de receta | H57: A5 o A6
A58: Papelería comercial | B58: Recetarios en color | C58: Talonario de recetas impreso full color. Mínimo 5 unidades. | D58: Recetarios en color | H58: A5 o A6
A59: Impresión digital | B59: Impresión color A4 | C59: Impresión full color en papel obra 75 g, de un lado. Se cobra por hoja y el precio baja por cantidad. | D59: Impresión color A4 simple faz | G59: imprimir, impresiones, copias en color | H59: A4
A60: Impresión digital | B60: Impresión color A4 doble faz | C60: Full color de los dos lados de la hoja. | D60: Impresión color A4 doble faz | H60: A4
A61: Impresión digital | B61: Impresión blanco y negro A4 | C61: Impresión en blanco y negro en papel obra 75 g, de un lado. Se cobra por hoja. | D61: Impresión blanco y negro A4 simple faz | G61: imprimir, impresiones, impresión de archivos, fotocopias | H61: A4
A62: Impresión digital | B62: Impresión blanco y negro A4 doble faz | C62: Blanco y negro de los dos lados de la hoja. Es lo que se usa para apuntes y material de estudio: se cuentan las hojas y se le suma el anillado. | D62: Impresión blanco y negro A4 doble faz | H62: A4
A63: Impresión digital | B63: Impresión color A3 | C63: Impresión láser full color en A3. Se cobra por hoja. | D63: Impresión color A3 | H63: A3
A64: Impresión digital | B64: Impresión blanco y negro A3 | C64: Impresión en blanco y negro en A3. Se cobra por hoja. | D64: Impresión blanco y negro A3 | H64: A3
A65: Impresión digital | B65: Impresión en papel ilustración | C65: Papel ilustración: más grueso y con terminación satinada. | D65: Impresión en papel ilustración | H65: A4
A66: Impresión digital | B66: Impresión en opalina | C66: Opalina: papel rígido y liso, para certificados y diplomas. | D66: Impresión en opalina | H66: A4
A67: Encuadernación y terminaciones | B67: Anillado plástico A4/Oficio | C67: Anillado con espiral plástico. Se cobra por unidad y no incluye la impresión. | D67: Anillado plástico A4/Oficio | G67: anillado, espiralado, espiral, encuadernado con anillo | H67: A4 u oficio
A68: Encuadernación y terminaciones | B68: Anillado metálico hasta 3/4 pulgada | C68: Anillado con espiral metálico wire-o. No incluye la impresión. | D68: Anillado metálico hasta 3/4 pulgada | G68: anillado, wire-o, wireo, espiral metalico, encuadernado con anillo metalico | H68: A4 o A3
A69: Encuadernación y terminaciones | B69: Armado de revistas | C69: Armado completo de revista o cuadernillo: plegado, refilado y 2 ganchos al centro. No incluye la impresión. | D69: Encuadernación abrochada | G69: armado de revistas, encuadernado a caballo, revista completa | H69: A4
A70: Encuadernación y terminaciones | B70: Encuadernación fresada | C70: Encuadernación pegada, tipo libro. No incluye la impresión. | D70: Encuadernación fresada | G70: encuadernación, empastado, tesis, libros | H70: A4
A71: Encuadernación y terminaciones | B71: Laminado A4 | C71: Plastificado fino sobre el impreso, mate o brillante. Se cobra por unidad. | D71: Laminado A4 | G71: laminado, plastificado, brillo, mate | H71: A4
A72: Encuadernación y terminaciones | B72: Plastificado de documentos A4 | C72: Plastificado rígido de documentos en A4. Se cobra por unidad. | D72: Plastificado A4 | G72: plastificado, laminado rígido, plastificar | H72: A4
A73: Encuadernación y terminaciones | B73: Plastificado de documentos oficio | C73: Plastificado rígido en tamaño oficio. | D73: Plastificado oficio | H73: oficio
A74: Encuadernación y terminaciones | B74: Plastificado de documentos A3 | C74: Plastificado rígido en A3. | D74: Plastificado A3 | H74: A3
A75: Encuadernación y terminaciones | B75: Plastificado de credencial o carnet 9x13 | C75: Plastificado de credenciales y carnets, 9x13 cm. | D75: Plastificado carnet | G75: credencial, carnet, plastificar carnet | H75: 9x13 cm
A76: Encuadernación y terminaciones | B76: Plastificado cocodrilo | C76: Plastificado cocodrilo, el formato más chico. | D76: Plastificado cocodrilo | G76: cocodrilo
A77: Encuadernación y terminaciones | B77: Puntillado | C77: Perforado para desprender a mano, sobre un impreso. Se usa en rifas y talonarios. Se cobra por pasada. | D77: Puntillado | G77: puntillado, perforado, linea de corte, rifas, talonarios, trazado troquelado manual de papel, pespunteado
A78: Encuadernación y terminaciones | B78: Colocación de ojalillos | C78: Colocación de ojalillos metálicos. Se cobra por ojalillo. | D78: Colocación de ojalillos | G78: ojales, ojalillos, arandelas
A79: Encuadernación y terminaciones | B79: Numerado correlativo | C79: Numeración correlativa sobre el impreso. | D79: Numerado correlativo | G79: numerado, numeración, correlativo
A80: Encuadernación y terminaciones | B80: 500 perforados o microperforados | C80: Perforado o microperforado. El precio es por los 500. | D80: Perforado x500 | G80: perforado, agujeros, microperforado
A81: Folletería y editorial | B81: 500 volantes A6 | C81: Volantes 10x15 cm full color. El precio es por los 500. | D81: Volantes A6 x500 | G81: volantes, flyers, panfletos, folletos | H81: A6 (10x15 cm)
A82: Folletería y editorial | B82: Libros de medicina | C82: Cuatro títulos puntuales: ROSS Histología, LANGMAN Embriología Médica, GUYTON & HALL Fisiología y MOORE Anatomía Clínica. Mismo precio cada uno, sin importar la cantidad de páginas. Solo estos cuatro. | D82: Libros de medicina | G82: ross, langman, guyton, hall, moore, histología, embriología, fisiología, anatomía, anatomía clínica
A83: Folletería y editorial | B83: Pack 4 libros de medicina | C83: Los cuatro libros juntos: ROSS, LANGMAN, GUYTON & HALL y MOORE. | D83: Pack 4 libros de medicina | G83: pack de libros, combo medicina, los 4 libros
A84: Folletería y editorial | B84: Anotadores personalizados | C84: Taco de anotador 10x15 cm impreso en negro. Se cobra por unidad. | D84: Anotadores personalizados en negro | G84: anotadores, tacos, blocks, libretas | H84: 10x15 cm
A85: Folletería y editorial | B85: Anotadores personalizados en color | C85: El mismo taco 10x15 cm, impreso full color. | D85: Anotadores personalizados en color | H85: 10x15 cm
A86: Gran formato y cartelería | B86: Posters A3 y A2 | C86: Poster impreso full color, A3 o A2. Se cobra por unidad. | D86: Posters A3 y A2 | G86: posters, afiches, láminas | H86: A3 o A2
A87: Gran formato y cartelería | B87: Banner roll-up 85x200 cm | C87: Banner enrollable con estructura de aluminio y bolso. Listo para usar. | D87: Banner roll-up | E87: 85 | F87: 200 | G87: roll up, banner enrollable
A88: Gran formato y cartelería | B88: Porta banner tipo X 90x190 cm | C88: Estructura tipo X con la lona impresa, 90x190 cm. Liviana y fácil de armar. | D88: Porta banner tipo X | E88: 90 | F88: 190 | G88: porta banner, araña, banner tipo x
A89: Señalética y punto de venta | B89: Cartelería de seguridad e higiene A3 | C89: Carteles reglamentarios de seguridad e higiene, en A3 (29,7x42 cm) sobre plástico corrugado. Este precio es solo para el A3; en otra medida se cotiza como cartel. | D89: Cartelería en plástico corrugado A3 | G89: cartel de seguridad, señalética, higiene y seguridad, cartel reglamentario | H89: A3
A90: Señalética y punto de venta | B90: Señalética de baños y accesos A3 | C90: Señalética de baños y accesos en A3 sobre plástico corrugado. Para interior también se puede en A4 plastificado. | D90: Cartelería en plástico corrugado A3 | G90: señalética, cartel de baño, cartel de acceso, señal | H90: A3
A91: Señalética y punto de venta | B91: Cartas y menús plastificados A4 | C91: Carta o menú A4 impreso y plastificado, para que aguante el uso diario. | D91: Cartas y menús plastificados | G91: cartas, menús, carta de restaurante | H91: A4
A92: Señalética y punto de venta | B92: Carteles de precios y ofertas A3 | C92: Cartel de precios u ofertas en A3: impresión color más plastificado. | D92: Impresión color más plastificado | G92: cartel de precios, cartel de oferta, cartel para el local | H92: A3
A93: Eventos y sociales | B93: 100 tarjetas de agradecimiento | C93: Tarjetas 9x5 cm para agradecer a los invitados. El precio es por las 100. | D93: Tarjetas 9x5 simple faz x100 | E93: 9 | F93: 5 | G93: tarjetas de agradecimiento, tarjetas de evento
A94: Carteles y vidrieras | B94: Vinilo microperforado para vidriera 1x1 m | C94: Vinilo microperforado para vidrieras: desde adentro se ve hacia afuera, desde afuera se ve la impresión. Se cotiza por metro cuadrado, mínimo medio m2. | D94: Vinilo microperforado | E94: 100 | F94: 100 | G94: microperforado, vinilo para vidriera, vinilo que se ve de adentro
A95: Carteles y vidrieras | B95: Cartel en PVC espumado 3 mm 50x70 cm | C95: Cartel en PVC espumado de 3 mm con vinilo brillo o mate. Más firme y durable que el plástico corrugado, que es la alternativa más económica. Se cotiza por metro cuadrado, mínimo medio m2. | D95: PVC espumado 3 mm con vinilo | E95: 50 | F95: 70 | G95: pvc, pvc espumado, cartel rigido, sintra, letrero
A96: Gran formato y cartelería | B96: Impresión de planos A1 | C96: Impresión de planos en papel obra 90 g, por metro cuadrado, mínimo medio m2. El precio depende de cuánta tinta cubre el dibujo: lineal (solo líneas), 25%, 50% o 100% de cobertura de color/relleno — decinos cuál para cotizar. | D96: Impresión de planos lineal | E96: 59.4 | F96: 84.1 | G96: planos, planos de obra, autocad, plotteo, ploteo de planos, plotter
A97: Diseño y servicios | B97: Escaneo de planos | C97: Escaneo y digitalización de planos en gran formato. Se cobra por metro lineal escaneado. También escaneamos A3. | D97: Escaneo de planos | G97: escanear, escaneo, digitalizar, escaneo de planos, pasar a digital | H97: A3
A98: Stickers con forma | B98: Plancha A4 de stickers | C98: Hoja A4 de stickers en papel autoadhesivo, con medio corte para despegarlos de a uno. Incluye la impresión y el corte. El precio baja bastante desde 2 planchas. | D98: Plancha A4 de stickers | G98: plancha de stickers, hoja de stickers, stickers en plancha, calcos en hoja | H98: A4
A99: Gran formato y cartelería | B99: Lona 1,9x0,9 m con porta banner 2 velas | C99: La lona impresa full color con bolsillos, más la estructura tipo araña de 2 velas. Se arma y se guarda en minutos. El precio incluye las dos cosas. | D99: Lona 1,9x0,9 m con porta banner 2 velas | G99: banner completo, kit de banner, lona con estructura, araña con lona, banner armado | H99: 1,9 x 0,9 m
A100: Gran formato y cartelería | B100: Lona 2x0,85 m con porta banner roll up | C100: La lona impresa full color más el roll up con estuche: la lona se enrolla dentro de la base. No lleva bolsillos. El precio incluye las dos cosas. | D100: Lona 2x0,85 m con porta banner roll up | G100: roll up, rollup con lona, banner enrollable, banner completo, kit de banner | H100: 2 x 0,85 m
A107: Encuadernación y terminaciones | B107: Laminado A3 | C107: Plastificado fino sobre el impreso, mate o brillante, en A3. Se cobra por unidad. | D107: Laminado A3 | G107: laminado, plastificado, brillo, mate | H107: A3
A108: Encuadernación y terminaciones | B108: Laminado por metro | C108: Plastificado fino sobre el impreso, mate o brillante, para piezas grandes. Se cobra por metro lineal. | D108: Laminado metro lineal | G108: laminado, plastificado, brillo, mate
A109: Encuadernación y terminaciones | B109: Encapsulado A4 | C109: Plastificado grueso de ambos lados sobre el impreso, en A4. Mas resistente que el laminado. Se cobra por unidad. | D109: Encapsulado A4 | G109: encapsulado, plastificado grueso | H109: A4
A110: Encuadernación y terminaciones | B110: Encapsulado A3 | C110: Plastificado grueso de ambos lados sobre el impreso, en A3. Se cobra por unidad. | D110: Encapsulado A3 | G110: encapsulado, plastificado grueso | H110: A3
A111: Encuadernación y terminaciones | B111: Encapsulado por metro | C111: Plastificado grueso de ambos lados, para piezas grandes. Se cobra por metro lineal. | D111: Encapsulado metro lineal | G111: encapsulado, plastificado grueso
A112: Encuadernación y terminaciones | B112: Anillado metálico 1 pulgada | C112: Anillado con espiral metalico wire-o, grosor 1 pulgada. No incluye la impresión. | D112: Anillado metálico 1 pulgada | G112: anillado, wire-o, wireo, espiral metalico | H112: A4 o A3
A113: Encuadernación y terminaciones | B113: Anillado metálico 1 1/8 pulgada | C113: Anillado con espiral metalico wire-o, grosor 1 1/8 pulgada. No incluye la impresión. | D113: Anillado metálico 1 1/8 pulgada | G113: anillado, wire-o, wireo, espiral metalico | H113: A4 o A3
A114: Encuadernación y terminaciones | B114: Anillado metálico 1 1/4 pulgada | C114: Anillado con espiral metalico wire-o, grosor 1 1/4 pulgada. No incluye la impresión. | D114: Anillado metálico 1 1/4 pulgada | G114: anillado, wire-o, wireo, espiral metalico | H114: A4 o A3
A115: Encuadernación y terminaciones | B115: Anillado metálico 1 1/2 pulgada | C115: Anillado con espiral metalico wire-o, grosor 1 1/2 pulgada. No incluye la impresión. | D115: Anillado metálico 1 1/2 pulgada | G115: anillado, wire-o, wireo, espiral metalico | H115: A4 o A3
A116: Encuadernación y terminaciones | B116: Anillado plástico A3 | C116: Anillado con espiral plástico en A3. Se cobra por unidad y no incluye la impresión. | D116: Anillado plástico A3 | G116: anillado, espiralado, espiral, encuadernado con anillo | H116: A3
A117: Impresión digital | B117: Impresión color A4 106gr | C117: Impresión full color en papel obra 106 gr (mas grueso que el estandar), de un lado. Se cobra por hoja y el precio baja por cantidad. | D117: Impresión color A4 106gr simple faz | G117: imprimir, impresiones, copias en color, papel grueso, obra 106 | H117: A4
A118: Impresión digital | B118: Impresión color A4 106gr doble faz | C118: Full color de los dos lados de la hoja, en papel obra 106 gr. | D118: Impresión color A4 106gr doble faz | G118: papel grueso, obra 106 | H118: A4
A119: Impresión digital | B119: Impresión blanco y negro A4 106gr | C119: Impresión en blanco y negro en papel obra 106 gr, de un lado. Se cobra por hoja. | D119: Impresión blanco y negro A4 106gr simple faz | G119: imprimir, impresiones, fotocopias, papel grueso, obra 106 | H119: A4
A120: Impresión digital | B120: Impresión blanco y negro A4 106gr doble faz | C120: Blanco y negro de los dos lados de la hoja, en papel obra 106 gr. | D120: Impresión blanco y negro A4 106gr doble faz | G120: papel grueso, obra 106 | H120: A4
A121: Gran formato y cartelería | B121: Plotter obra 90gr | C121: Impresión de planos y dibujos tecnicos en papel obra 90 gr, por metro cuadrado, minimo medio m2. El precio depende de cuanta tinta cubre el dibujo: lineal (solo lineas, mas barato), 25%, 50% o 100% de cobertura de color/relleno. | D121: Impresión de planos lineal | G121: plotter, plotteo, planos, autocad, dibujo tecnico, lineal
A122: Gran formato y cartelería | B122: Plotter papel vegetal | C122: Impresión de planos en papel vegetal (translucido), por metro cuadrado, minimo medio m2. Precio segun cobertura: lineal, 25%, 50% o 100%. | D122: Plotter papel vegetal lineal | G122: plotter, plotteo, planos, vegetal, papel calco
A123: Gran formato y cartelería | B123: Plotter papel 130gr recubierto/encapado | C123: Impresión de planos en papel 130 gr recubierto/encapado, por metro cuadrado, minimo medio m2. Precio segun cobertura: lineal, 25%, 50% o 100%. | D123: Plotter papel 130gr recubierto/encapado lineal | G123: plotter, plotteo, planos, papel recubierto, papel encapado
A124: Gran formato y cartelería | B124: Impresión Autocad lineal A4 | C124: Impresión de plano o dibujo tecnico lineal (color o negro) en hoja A4. | D124: Autocad lineal A4 | G124: autocad, plano chico, dibujo tecnico | H124: A4
...

Sheet Materiales
A1: Material | B1: Unidad | C1: Desde | D1: Hasta | E1: Precio por unidad | F1: Mínimo facturable | G1: Nota | H1: Área útil ancho (cm) | I1: Área útil alto (cm) | J1: Separación (cm) | K1: Sin mínimo por trabajo | L1: Familia | M1: Piezas por paquete | N1: Precio total por tramo
A2: Papel autoadhesivo troquelado o medio corte | B2: pliego A3 | C2: 1 | D2: 1 | E2: 2500 | H2: 28 | I2: 44 | J2: 0.3
A3: Papel autoadhesivo troquelado o medio corte | B3: pliego A3 | C3: 2 | D3: 10 | E3: 2200
A4: Papel autoadhesivo troquelado o medio corte | B4: pliego A3 | C4: 11 | D4: 50 | E4: 2000
A5: Papel autoadhesivo troquelado o medio corte | B5: pliego A3 | C5: 51 | D5: 100 | E5: 1900
A6: Papel autoadhesivo troquelado o medio corte | B6: pliego A3 | C6: 101 | E6: 1710
A7: Papel autoadhesivo solo impresión | B7: pliego A3 | C7: 1 | D7: 100 | E7: 1800 | H7: 31 | I7: 46 | J7: 0
A8: Papel autoadhesivo solo impresión | B8: pliego A3 | C8: 101 | E8: 1620
A9: OPP brillo | B9: pliego A3 | C9: 1 | D9: 9 | E9: 2400 | H9: 31 | I9: 46 | J9: 0
A10: OPP brillo | B10: pliego A3 | C10: 10 | D10: 29 | E10: 2160
A11: OPP brillo | B11: pliego A3 | C11: 30 | E11: 1920
A12: OPP brillo troquelado | B12: pliego A3 | C12: 1 | D12: 9 | E12: 2800 | H12: 28 | I12: 44 | J12: 0.3
A13: OPP brillo troquelado | B13: pliego A3 | C13: 10 | D13: 29 | E13: 2520
A14: OPP brillo troquelado | B14: pliego A3 | C14: 30 | E14: 2240
A15: OPP plata, holográfico, cristal o mate | B15: pliego A3 | C15: 1 | D15: 9 | E15: 2600 | H15: 31 | I15: 46 | J15: 0
A16: OPP plata, holográfico, cristal o mate | B16: pliego A3 | C16: 10 | D16: 29 | E16: 2340
A17: OPP plata, holográfico, cristal o mate | B17: pliego A3 | C17: 30 | E17: 2080
A18: OPP plata, holográfico, cristal o mate troquelado | B18: pliego A3 | C18: 1 | D18: 9 | E18: 3000 | H18: 28 | I18: 44 | J18: 0.3
A19: OPP plata, holográfico, cristal o mate troquelado | B19: pliego A3 | C19: 10 | D19: 29 | E19: 2700
A20: OPP plata, holográfico, cristal o mate troquelado | B20: pliego A3 | C20: 30 | E20: 2400
A21: Lona | B21: m2 | C21: 1 | E21: 16000 | F21: 0.5
A22: Vinilo y lona UV | B22: m2 | C22: 1 | E22: 22000 | F22: 0.5
A23: Vinilo y lona UV con blanco o barniz | B23: m2 | C23: 1 | E23: 26000 | F23: 0.5
A24: Vinilo UV montado en corrugado | B24: m2 | C24: 1 | E24: 30000 | F24: 0.5
A25: Vinilo UV troquelado | B25: m2 | C25: 1 | E25: 28000 | F25: 0.5
A26: Tarjetas 9x5 simple faz x100 | B26: paquete de 100 tarjetas | C26: 1 | E26: 13200 | L26: Tarjetas 9x5 simple faz
A27: Tarjetas 9x5 simple faz encapsuladas x100 | B27: paquete de 100 tarjetas | C27: 1 | E27: 16500 | L27: Tarjetas 9x5 simple faz encapsuladas
A28: Tarjetas 9x5 doble faz x100 | B28: paquete de 100 tarjetas | C28: 1 | E28: 16500 | L28: Tarjetas 9x5 doble faz
A29: Tarjetas 9x5 doble faz encapsuladas x100 | B29: paquete de 100 tarjetas | C29: 1 | E29: 18700 | L29: Tarjetas 9x5 doble faz encapsuladas
A30: Tarjetas 9x5 kraft simple faz x100 | B30: paquete de 100 tarjetas | C30: 1 | E30: 17600 | L30: Tarjetas 9x5 kraft simple faz
A31: Tarjetas 9x5 kraft doble faz x100 | B31: paquete de 100 tarjetas | C31: 1 | E31: 24200 | L31: Tarjetas 9x5 kraft doble faz
A32: Tarjetas 9x5 simple faz x500 | B32: paquete de 500 tarjetas | C32: 1 | E32: 28000 | L32: Tarjetas 9x5 simple faz
A33: Tarjetas 9x5 simple faz encapsuladas x500 | B33: paquete de 500 tarjetas | C33: 1 | E33: 38000 | L33: Tarjetas 9x5 simple faz encapsuladas
A34: Tarjetas 9x5 doble faz x500 | B34: paquete de 500 tarjetas | C34: 1 | E34: 38000 | L34: Tarjetas 9x5 doble faz
A35: Tarjetas 9x5 doble faz encapsuladas x500 | B35: paquete de 500 tarjetas | C35: 1 | E35: 45000 | L35: Tarjetas 9x5 doble faz encapsuladas
A36: Tarjetas 9x5 simple faz x1000 | B36: paquete de 1000 tarjetas | C36: 1 | E36: 42000 | L36: Tarjetas 9x5 simple faz
A37: Tarjetas 9x5 simple faz encapsuladas x1000 | B37: paquete de 1000 tarjetas | C37: 1 | E37: 54000 | L37: Tarjetas 9x5 simple faz encapsuladas
... A39: Tarjetas 9x5 doble faz encapsuladas x1000 | B39: paquete de 1000 tarjetas | C39: 1 | E39: 59000 | L39: Tarjetas 9x5 doble faz encapsuladas
A40: Hojas membretadas A4 x500 | B40: paquete de 500 hojas | C40: 1 | E40: 35000
A41: Sobres impresos x100 | B41: paquete de 100 sobres | C41: 1 | E41: 25000
A42: Talonarios x10 | B42: paquete de 10 talonarios | C42: 1 | E42: 54000
A43: Sobres oficio inglés | B43: unidad | C43: 1 | D43: 200 | E43: 250 | K43: sí
A44: Sobres oficio inglés | B44: unidad | C44: 201 | D44: 500 | E44: 220
A45: Sobres oficio inglés | B45: unidad | C45: 501 | D45: 1000 | E45: 190
A46: Sobres oficio inglés | B46: unidad | C46: 1001 | E46: 180
A47: Carpetas institucionales sin laminar | B47: unidad | C47: 1 | D47: 20 | E47: 2600 | K47: sí
A48: Carpetas institucionales sin laminar | B48: unidad | C48: 21 | D48: 50 | E48: 2500
A49: Carpetas institucionales sin laminar | B49: unidad | C49: 51 | D49: 100 | E49: 2300
A50: Carpetas institucionales sin laminar | B50: unidad | C50: 101 | D50: 300 | E50: 2100
A51: Carpetas institucionales sin laminar | B51: unidad | C51: 301 | E51: 1900
A52: Carpetas institucionales laminadas | B52: unidad | C52: 1 | D52: 20 | E52: 3000 | K52: sí
A53: Carpetas institucionales laminadas | B53: unidad | C53: 21 | D53: 50 | E53: 2800
A54: Carpetas institucionales laminadas | B54: unidad | C54: 51 | D54: 100 | E54: 2600
A55: Carpetas institucionales laminadas | B55: unidad | C55: 101 | D55: 300 | E55: 2400
A56: Carpetas institucionales laminadas | B56: unidad | C56: 301 | E56: 2300
A57: Recetarios en negro | B57: unidad | C57: 1 | D57: 10 | E57: 4000 | K57: sí
A58: Recetarios en negro | B58: unidad | C58: 11 | D58: 20 | E58: 3400
A59: Recetarios en negro | B59: unidad | C59: 21 | D59: 50 | E59: 3000
A60: Recetarios en negro | B60: unidad | C60: 51 | E60: 2600
A61: Recetarios en color | B61: unidad | C61: 1 | D61: 10 | E61: 4500 | K61: sí
A62: Recetarios en color | B62: unidad | C62: 11 | D62: 20 | E62: 3800
A63: Recetarios en color | B63: unidad | C63: 21 | D63: 50 | E63: 3200
A64: Recetarios en color | B64: unidad | C64: 51 | E64: 2800
A65: Impresión color A4 simple faz | B65: hoja | C65: 1 | D65: 70 | E65: 400 | K65: sí
A66: Impresión color A4 simple faz | B66: hoja | C66: 71 | D66: 150 | E66: 150
A67: Impresión color A4 simple faz | B67: hoja | C67: 151 | D67: 500 | E67: 80
A68: Impresión color A4 simple faz | B68: hoja | C68: 501 | E68: 70
A69: Impresión color A4 doble faz | B69: hoja | C69: 1 | D69: 70 | E69: 600 | K69: sí
A70: Impresión color A4 doble faz | B70: hoja | C70: 71 | D70: 150 | E70: 200
A71: Impresión color A4 doble faz | B71: hoja | C71: 151 | D71: 500 | E71: 120
A72: Impresión color A4 doble faz | B72: hoja | C72: 501 | E72: 110
A73: Impresión blanco y negro A4 simple faz | B73: hoja | C73: 1 | D73: 10 | E73: 100 | K73: sí
A74: Impresión blanco y negro A4 simple faz | B74: hoja | C74: 11 | E74: 70
A75: Impresión blanco y negro A4 doble faz | B75: hoja | C75: 1 | D75: 10 | E75: 150 | K75: sí
A76: Impresión blanco y negro A4 doble faz | B76: hoja | C76: 11 | D76: 100 | E76: 96
A77: Impresión blanco y negro A4 doble faz | B77: hoja | C77: 101 | D77: 500 | E77: 88
A78: Impresión blanco y negro A4 doble faz | B78: hoja | C78: 501 | D78: 1000 | E78: 86
A79: Impresión blanco y negro A4 doble faz | B79: hoja | C79: 1001 | E79: 84
A80: Impresión color A3 | B80: hoja | C80: 1 | E80: 1200 | K80: sí
A81: Impresión blanco y negro A3 | B81: hoja | C81: 1 | E81: 600 | K81: sí
A82: Impresión en papel ilustración | B82: hoja | C82: 1 | E82: 800 | K82: sí
A83: Impresión en opalina | B83: hoja | C83: 1 | E83: 900 | K83: sí
A84: Anillado plástico A4/Oficio | B84: unidad | C84: 1 | E84: 2400 | K84: sí | L84: Anillado plástico
A85: Anillado metálico hasta 3/4 pulgada | B85: unidad | C85: 1 | E85: 3200 | K85: sí | L85: Anillado metálico
A86: Encuadernación abrochada | B86: unidad | C86: 1 | E86: 2000 | K86: sí
A87: Encuadernación fresada | B87: unidad | C87: 1 | D87: 1 | E87: 7000
A88: Encuadernación fresada | B88: unidad | C88: 2 | D88: 10 | E88: 5000
A89: Laminado A4 | B89: unidad | C89: 1 | E89: 330 | K89: sí | L89: Laminado
A90: Plastificado A4 | B90: unidad | C90: 1 | E90: 2200 | K90: sí | L90: Plastificado de documentos
A91: Plastificado oficio | B91: unidad | C91: 1 | E91: 2400 | K91: sí | L91: Plastificado de documentos
A92: Plastificado A3 | B92: unidad | C92: 1 | E92: 3000 | K92: sí | L92: Plastificado de documentos
A93: Plastificado carnet | B93: unidad | C93: 1 | E93: 1500 | K93: sí | L93: Plastificado de documentos
A94: Plastificado cocodrilo | B94: unidad | C94: 1 | E94: 800 | K94: sí | L94: Plastificado de documentos
A95: Puntillado | B95: unidad | C95: 1 | E95: 50 | G95: Perforado para desprender (rifas, talonarios). No es troquelado ni corte a medida. | K95: sí
A96: Colocación de ojalillos | B96: unidad | C96: 1 | E96: 1000 | K96: sí
A97: Numerado correlativo | B97: unidad | C97: 1 | E97: 5000
A98: Perforado x500 | B98: paquete de 500 perforados | C98: 1 | E98: 4000
A99: Volantes A6 x500 | B99: paquete de 500 volantes | C99: 1 | E99: 12000
A100: Libros de medicina | B100: unidad | C100: 1 | E100: 30000
A101: Pack 4 libros de medicina | B101: pack | C101: 1 | E101: 99000
...

Sheet Pendientes
A1: Producto | B1: Descripción | C1: Cómo se cobra | D1: Notas

Sheet Parámetros
A1: Parámetro | B1: Valor | C1: Nota
A2: Mínimo por trabajo | B2: 4000 | C2: Ningún trabajo se cobra menos que esto.
A3: Redondeo | B3: 100 | C3: El total final se redondea al múltiplo de $100 más cercano.
A4: Moneda | B4: ARS | C4: Pesos argentinos, IVA incluido.

Sheet Casos de prueba
A1: Pedido | B1: Cantidad | C1: Material | D1: Ancho (cm) | E1: Alto (cm) | F1: Piezas por unidad de cobro | G1: Precio correcto
A2: 250 stickers 3x3 cm | B2: 250 | C2: Papel autoadhesivo troquelado o medio corte | D2: 3 | E2: 3 | F2: 104 | G2: 6600
A3: 250 etiquetas para frascos 6x3 cm | B3: 250 | C3: Papel autoadhesivo troquelado o medio corte | D3: 6 | E3: 3 | F3: 56 | G3: 11000
A4: 100 stickers 5x5 cm | B4: 100 | C4: Papel autoadhesivo troquelado o medio corte | D4: 5 | E4: 5 | F4: 40 | G4: 6600
A5: 100 stickers redondos de 5 cm | B5: 100 | C5: Papel autoadhesivo troquelado o medio corte | D5: 5 | E5: 5 | F5: 40 | G5: 6600
A6: 100 stickers en OPP brillo 5x5 cm | B6: 100 | C6: OPP brillo troquelado | D6: 5 | E6: 5 | F6: 40 | G6: 8400
A7: 100 stickers holográficos 5x5 cm | B7: 100 | C7: OPP plata, holográfico, cristal o mate troquelado | D7: 5 | E7: 5 | F7: 40 | G7: 9000
A8: 250 stickers 5x5 cm | B8: 250 | C8: Papel autoadhesivo troquelado o medio corte | D8: 5 | E8: 5 | F8: 40 | G8: 15400
A9: 250 stickers redondos de 5 cm | B9: 250 | C9: Papel autoadhesivo troquelado o medio corte | D9: 5 | E9: 5 | F9: 40 | G9: 15400
A10: 500 stickers 5x5 cm | B10: 500 | C10: Papel autoadhesivo troquelado o medio corte | D10: 5 | E10: 5 | F10: 40 | G10: 26000
A11: 100 etiquetas 9x5 cm | B11: 100 | C11: Papel autoadhesivo troquelado o medio corte | D11: 9 | E11: 5 | F11: 24 | G11: 11000
A12: 100 etiquetas en OPP brillo 9x5 cm | B12: 100 | C12: OPP brillo troquelado | D12: 9 | E12: 5 | F12: 24 | G12: 14000
A13: 100 stickers 7x7 cm | B13: 100 | C13: Papel autoadhesivo troquelado o medio corte | D13: 7 | E13: 7 | F13: 18 | G13: 13200
... A21: 100 etiquetas 14x10 cm | B21: 100 | C21: Papel autoadhesivo troquelado o medio corte | D21: 14 | E21: 10 | F21: 6 | G21: 34000
A22: 100 stickers en vinilo UV 5x5 cm | B22: 100 | C22: Vinilo UV troquelado | D22: 5 | E22: 5 | G22: 14000
A23: 250 stickers en vinilo UV 5x5 cm | B23: 250 | C23: Vinilo UV troquelado | D23: 5 | E23: 5 | G23: 17500
A24: 100 stickers en vinilo UV 7x7 cm | B24: 100 | C24: Vinilo UV troquelado | D24: 7 | E24: 7 | G24: 14000
A25: 100 stickers en vinilo UV 10x10 cm | B25: 100 | C25: Vinilo UV troquelado | D25: 10 | E25: 10 | G25: 28000
A26: 50 etiquetas en vinilo UV 14x10 cm | B26: 50 | C26: Vinilo UV troquelado | D26: 14 | E26: 10 | G26: 19600
A27: 100 etiquetas en vinilo UV 14x10 cm | B27: 100 | C27: Vinilo UV troquelado | D27: 14 | E27: 10 | G27: 39200
A28: Cartel adhesivo 50x70 cm | B28: 1 | C28: Vinilo y lona UV | D28: 50 | E28: 70 | G28: 11000
A29: Cartel rígido 50x70 cm | B29: 1 | C29: Vinilo UV montado en corrugado | D29: 50 | E29: 70 | G29: 15000
A30: Cartel adhesivo 70x100 cm | B30: 1 | C30: Vinilo y lona UV | D30: 70 | E30: 100 | G30: 15400
A31: Cartel rígido 70x100 cm | B31: 1 | C31: Vinilo UV montado en corrugado | D31: 70 | E31: 100 | G31: 21000
A32: Vinilo para vidriera 1x1 m | B32: 1 | C32: Vinilo y lona UV | D32: 100 | E32: 100 | G32: 22000
A33: Cartel rígido 1x1 m | B33: 1 | C33: Vinilo UV montado en corrugado | D33: 100 | E33: 100 | G33: 30000
... A40: Banner de lona 4x1 m | B40: 1 | C40: Lona | D40: 400 | E40: 100 | G40: 64000
A41: 500 stickers 2x2 cm (medida libre) | B41: 500 | C41: Papel autoadhesivo troquelado o medio corte | D41: 2 | E41: 2 | F41: 228 | G41: 6600
A42: 100 etiquetas 5x8 cm (medida libre) | B42: 100 | C42: Papel autoadhesivo troquelado o medio corte | D42: 5 | E42: 8 | F42: 25 | G42: 8800
A43: 80 etiquetas 20x6 cm (gana la orientación rotada) | B43: 80 | C43: Papel autoadhesivo troquelado o medio corte | D43: 20 | E43: 6 | F43: 8 | G43: 22000
A44: 300 etiquetas 4x4 cm solo impresión (sin separación) | B44: 300 | C44: Papel autoadhesivo solo impresión | D44: 4 | E44: 4 | F44: 77 | G44: 7200
A45: 20 stickers 30x45 cm (no entra en el pliego) | B45: 20 | C45: Papel autoadhesivo troquelado o medio corte | D45: 30 | E45: 45 | F45: 0 | G45: Derivar a consulta: no entra en el pliego
A46: 10 stickers 3x3 cm (activa el mínimo por trabajo) | B46: 10 | C46: Papel autoadhesivo troquelado o medio corte | D46: 3 | E46: 3 | F46: 104 | G46: 4000
A47: 1 lona de 90x60 cm (activa el redondeo) | B47: 1 | C47: Lona | D47: 90 | E47: 60 | G47: 8600
A48: 100 tarjetas 9x5 simple faz | B48: 100 | C48: Tarjetas 9x5 simple faz x100 | D48: 9 | E48: 5 | G48: 13200
A49: 500 tarjetas 9x5 doble faz | B49: 500 | C49: Tarjetas 9x5 doble faz x500 | D49: 9 | E49: 5 | G49: 38000
A50: 1000 tarjetas 9x5 simple faz encapsuladas | B50: 1000 | C50: Tarjetas 9x5 simple faz encapsuladas x1000 | D50: 9 | E50: 5 | G50: 54000
A51: 500 hojas membretadas A4 | B51: 500 | C51: Hojas membretadas A4 x500 | D51: 21 | E51: 29.7 | G51: 35000
A52: 10 talonarios de factura | B52: 10 | C52: Talonarios x10 | D52: 15 | E52: 21 | G52: 54000
A53: 500 volantes A6 | B53: 500 | C53: Volantes A6 x500 | D53: 10 | E53: 15 | G53: 12000
A54: 1 banner roll-up 85x200 | B54: 1 | C54: Banner roll-up | D54: 85 | E54: 200 | G54: 38000
A55: 250 sobres oficio inglés | B55: 250 | C55: Sobres oficio inglés | D55: 23.5 | E55: 12 | G55: 55000
A56: 150 sobres oficio inglés (tramo 1-200) | B56: 150 | C56: Sobres oficio inglés | D56: 23.5 | E56: 12 | G56: 37500
A57: 600 sobres oficio inglés (tramo 501-1000) | B57: 600 | C57: Sobres oficio inglés | D57: 23.5 | E57: 12 | G57: 114000
A58: 1200 sobres oficio inglés (tramo 1001+) | B58: 1200 | C58: Sobres oficio inglés | D58: 23.5 | E58: 12 | G58: 216000
... A86: 4 planos A1 | B86: 4 | C86: Impresión de planos lineal | D86: 59.4 | E86: 84.1 | G86: 14000
A87: escaneo de 3 metros de planos | B87: 3 | C87: Escaneo de planos | G87: 24000
A88: escaneo de 1 metro de planos | B88: 1 | C88: Escaneo de planos | G88: 8000
A89: 1 plancha A4 de stickers | B89: 1 | C89: Plancha A4 de stickers | G89: 4000
A90: 10 planchas A4 de stickers | B90: 10 | C90: Plancha A4 de stickers | G90: 14000
A91: 150 planchas A4 de stickers | B91: 150 | C91: Plancha A4 de stickers | G91: 150000
A92: 1 lona 1,9x0,9 con porta banner 2 velas | B92: 1 | C92: Lona 1,9x0,9 m con porta banner 2 velas | G92: 61400
A93: 1 lona 2x0,85 con roll up | B93: 1 | C93: Lona 2x0,85 m con porta banner roll up | G93: 65200
A94: 2 lonas 2x0,85 con roll up | B94: 2 | C94: Lona 2x0,85 m con porta banner roll up | G94: 130400
A95: 100 stickers en OPP brillo sin cortar de 8x8 cm | B95: 100 | C95: OPP brillo | D95: 8 | E95: 8 | F95: 15 | G95: 16800
A96: 100 stickers holográficos sin cortar de 8x8 cm | B96: 100 | C96: OPP plata, holográfico, cristal o mate | D96: 8 | E96: 8 | F96: 15 | G96: 18200
A97: 1 cartel adhesivo con blanco de 60x80 cm | B97: 1 | C97: Vinilo y lona UV con blanco o barniz | D97: 60 | E97: 80 | G97: 13000
A98: 100 tarjetas 9x5 simple faz encapsuladas | B98: 100 | C98: Tarjetas 9x5 simple faz encapsuladas x100 | D98: 9 | E98: 5 | G98: 16500
A99: 100 tarjetas 9x5 doble faz | B99: 100 | C99: Tarjetas 9x5 doble faz x100 | D99: 9 | E99: 5 | G99: 16500
A100: 100 tarjetas 9x5 doble faz encapsuladas | B100: 100 | C100: Tarjetas 9x5 doble faz encapsuladas x100 | D100: 9 | E100: 5 | G100: 18700
A101: 100 tarjetas 9x5 en papel kraft simple faz | B101: 100 | C101: Tarjetas 9x5 kraft simple faz x100 | D101: 9 | E101: 5 | G101: 17600
A102: 100 tarjetas 9x5 en papel kraft doble faz | B102: 100 | C102: Tarjetas 9x5 kraft doble faz x100 | D102: 9 | E102: 5 | G102: 24200
A103: 500 tarjetas 9x5 simple faz | B103: 500 | C103: Tarjetas 9x5 simple faz x500 | D103: 9 | E103: 5 | G103: 28000
A104: 500 tarjetas 9x5 simple faz encapsuladas | B104: 500 | C104: Tarjetas 9x5 simple faz encapsuladas x500 | D104: 9 | E104: 5 | G104: 38000
A105: 500 tarjetas 9x5 doble faz encapsuladas | B105: 500 | C105: Tarjetas 9x5 doble faz encapsuladas x500 | D105: 9 | E105: 5 | G105: 45000
A106: 1000 tarjetas 9x5 simple faz | B106: 1000 | C106: Tarjetas 9x5 simple faz x1000 | D106: 9 | E106: 5 | G106: 42000
A107: 1000 tarjetas 9x5 doble faz | B107: 1000 | C107: Tarjetas 9x5 doble faz x1000 | D107: 9 | E107: 5 | G107: 54000
A108: 1000 tarjetas 9x5 doble faz encapsuladas | B108: 1000 | C108: Tarjetas 9x5 doble faz encapsuladas x1000 | D108: 9 | E108: 5 | G108: 59000
A109: 100 sobres impresos con el logo | B109: 100 | C109: Sobres impresos x100 | D109: 21 | E109: 11 | G109: 25000
A110: 500 perforados | B110: 500 | C110: Perforado x500 | G110: 4000
A111: 5 recetarios en negro | B111: 5 | C111: Recetarios en negro | G111: 20000
A112: 5 recetarios en color | B112: 5 | C112: Recetarios en color | G112: 22500
A113: 50 impresiones color A4 doble faz | B113: 50 | C113: Impresión color A4 doble faz | D113: 21 | E113: 29.7 | G113: 30000
A114: 10 impresiones color A3 | B114: 10 | C114: Impresión color A3 | D114: 29.7 | E114: 42 | G114: 12000
A115: 5 impresiones blanco y negro A3 | B115: 5 | C115: Impresión blanco y negro A3 | D115: 29.7 | E115: 42 | G115: 3000
A116: 20 impresiones en papel ilustración | B116: 20 | C116: Impresión en papel ilustración | D116: 21 | E116: 29.7 | G116: 16000
A117: 15 impresiones en opalina | B117: 15 | C117: Impresión en opalina | D117: 21 | E117: 29.7 | G117: 13500
A118: 5 anillados metálicos wire-o | B118: 5 | C118: Anillado metálico hasta 3/4 pulgada | D118: 21 | E118: 29.7 | G118: 16000
A119: 10 encuadernaciones abrochadas | B119: 10 | C119: Encuadernación abrochada | D119: 21 | E119: 29.7 | G119: 20000
A120: 3 encuadernaciones fresadas | B120: 3 | C120: Encuadernación fresada | D120: 21 | E120: 29.7 | G120: 15000
A121: 1 plastificado oficio | B121: 1 | C121: Plastificado oficio | D121: 22 | E121: 33 | G121: 2400
A123: 20 numerados correlativos en unas entradas | B123: 20 | C123: Numerado correlativo | G123: 100000
A124: 1 libro de medicina, el de Guyton | B124: 1 | C124: Libros de medicina | G124: 30000
A125: el pack de los 4 libros de medicina | B125: 1 | C125: Pack 4 libros de medicina | G125: 99000
A126: 5 anotadores personalizados en negro | B126: 5 | C126: Anotadores personalizados en negro | D126: 10 | E126: 15 | G126: 20000
A127: 2 posters A3 | B127: 2 | C127: Posters A3 y A2 | D127: 29.7 | E127: 42 | G127: 3200
A128: 1 porta banner tipo X | B128: 1 | C128: Porta banner tipo X | D128: 90 | E128: 190 | G128: 32000
A129: 1 cartel de seguridad e higiene A3 | B129: 1 | C129: Cartelería en plástico corrugado A3 | D129: 29.7 | E129: 42 | G129: 10500
A130: 4 cartas plastificadas A4 para el menú | B130: 4 | C130: Cartas y menús plastificados | D130: 21 | E130: 29.7 | G130: 10400
A131: 1 cartel de precios A3 con plastificado | B131: 1 | C131: Impresión color más plastificado | D131: 29.7 | E131: 42 | G131: 4800
A132: escaneo de 2,45 metros de planos (medida con decimales) | B132: 2.45 | C132: Escaneo de planos | G132: 19600
A133: escaneo de 0,5 metros de planos (activa el mínimo por trabajo) | B133: 0.5 | C133: Escaneo de planos | G133: 4000
A134: 1 corte a medida | B134: 1 | C134: Corte a medida | G134: 5000
A135: 8 cortes a medida | B135: 8 | C135: Corte a medida | G135: 5000
A136: 50 cortes a medida | B136: 50 | C136: Corte a medida | G136: 5000
A137: 1 troquelado | B137: 1 | C137: Troquelado (corte con forma en papel) | G137: 10000
A138: 3 troquelados | B138: 3 | C138: Troquelado (corte con forma en papel) | G138: 10000
A139: 9 troquelados | B139: 9 | C139: Troquelado (corte con forma en papel) | G139: 10000
A140: 10 troquelados | B140: 10 | C140: Troquelado (corte con forma en papel) | G140: 10000
A141: 11 troquelados | B141: 11 | C141: Troquelado (corte con forma en papel) | G141: 11000
...

Sheet _listas
A1: Materiales — desplegable de Productos | B1: Colecciones — desplegable de Productos
A2: {=IFERROR(INDEX(Materiales!$A$2:$A$600,MATCH(0,COUNTIF($A$1:A1,Materiales!$A$2:$A$600)+IF(Materiales!$A$2:$A$600="",1,0),0)),"")} | B2: {=IFERROR(INDEX(Colecciones!$A$2:$A$600,MATCH(0,COUNTIF($B$1:B1,Colecciones!$A$2:$A$600)+IF(Colecciones!$A$2:$A$600="",1,0),0)),"")}
A3: {=IFERROR(INDEX(Materiales!$A$2:$A$600,MATCH(0,COUNTIF($A$1:A2,Materiales!$A$2:$A$600)+IF(Materiales!$A$2:$A$600="",1,0),0)),"")} | B3: {=IFERROR(INDEX(Colecciones!$A$2:$A$600,MATCH(0,COUNTIF($B$1:B2,Colecciones!$A$2:$A$600)+IF(Colecciones!$A$2:$A$600="",1,0),0)),"")}
A4: {=IFERROR(INDEX(Materiales!$A$2:$A$600,MATCH(0,COUNTIF($A$1:A3,Materiales!$A$2:$A$600)+IF(Materiales!$A$2:$A$600="",1,0),0)),"")} | B4: {=IFERROR(INDEX(Colecciones!$A$2:$A$600,MATCH(0,COUNTIF($B$1:B3,Colecciones!$A$2:$A$600)+IF(Colecciones!$A$2:$A$600="",1,0),0)),"")}
A5: {=IFERROR(INDEX(Materiales!$A$2:$A$600,MATCH(0,COUNTIF($A$1:A4,Materiales!$A$2:$A$600)+IF(Materiales!$A$2:$A$600="",1,0),0)),"")} | B5: {=IFERROR(INDEX(Colecciones!$A$2:$A$600,MATCH(0,COUNTIF($B$1:B4,Colecciones!$A$2:$A$600)+IF(Colecciones!$A$2:$A$600="",1,0),0)),"")}
A6: {=IFERROR(INDEX(Materiales!$A$2:$A$600,MATCH(0,COUNTIF($A$1:A5,Materiales!$A$2:$A$600)+IF(Materiales!$A$2:$A$600="",1,0),0)),"")} | B6: {=IFERROR(INDEX(Colecciones!$A$2:$A$600,MATCH(0,COUNTIF($B$1:B5,Colecciones!$A$2:$A$600)+IF(Colecciones!$A$2:$A$600="",1,0),0)),"")}
A7: {=IFERROR(INDEX(Materiales!$A$2:$A$600,MATCH(0,COUNTIF($A$1:A6,Materiales!$A$2:$A$600)+IF(Materiales!$A$2:$A$600="",1,0),0)),"")} | B7: {=IFERROR(INDEX(Colecciones!$A$2:$A$600,MATCH(0,COUNTIF($B$1:B6,Colecciones!$A$2:$A$600)+IF(Colecciones!$A$2:$A$600="",1,0),0)),"")}
A8: {=IFERROR(INDEX(Materiales!$A$2:$A$600,MATCH(0,COUNTIF($A$1:A7,Materiales!$A$2:$A$600)+IF(Materiales!$A$2:$A$600="",1,0),0)),"")} | B8: {=IFERROR(INDEX(Colecciones!$A$2:$A$600,MATCH(0,COUNTIF($B$1:B7,Colecciones!$A$2:$A$600)+IF(Colecciones!$A$2:$A$600="",1,0),0)),"")}
A9: {=IFERROR(INDEX(Materiales!$A$2:$A$600,MATCH(0,COUNTIF($A$1:A8,Materiales!$A$2:$A$600)+IF(Materiales!$A$2:$A$600="",1,0),0)),"")} | B9: {=IFERROR(INDEX(Colecciones!$A$2:$A$600,MATCH(0,COUNTIF($B$1:B8,Colecciones!$A$2:$A$600)+IF(Colecciones!$A$2:$A$600="",1,0),0)),"")}
A10: {=IFERROR(INDEX(Materiales!$A$2:$A$600,MATCH(0,COUNTIF($A$1:A9,Materiales!$A$2:$A$600)+IF(Materiales!$A$2:$A$600="",1,0),0)),"")} | B10: {=IFERROR(INDEX(Colecciones!$A$2:$A$600,MATCH(0,COUNTIF($B$1:B9,Colecciones!$A$2:$A$600)+IF(Colecciones!$A$2:$A$600="",1,0),0)),"")}
A11: {=IFERROR(INDEX(Materiales!$A$2:$A$600,MATCH(0,COUNTIF($A$1:A10,Materiales!$A$2:$A$600)+IF(Materiales!$A$2:$A$600="",1,0),0)),"")} | B11: {=IFERROR(INDEX(Colecciones!$A$2:$A$600,MATCH(0,COUNTIF($B$1:B10,Colecciones!$A$2:$A$600)+IF(Colecciones!$A$2:$A$600="",1,0),0)),"")}
A12: {=IFERROR(INDEX(Materiales!$A$2:$A$600,MATCH(0,COUNTIF($A$1:A11,Materiales!$A$2:$A$600)+IF(Materiales!$A$2:$A$600="",1,0),0)),"")} | B12: {=IFERROR(INDEX(Colecciones!$A$2:$A$600,MATCH(0,COUNTIF($B$1:B11,Colecciones!$A$2:$A$600)+IF(Colecciones!$A$2:$A$600="",1,0),0)),"")}
A13: {=IFERROR(INDEX(Materiales!$A$2:$A$600,MATCH(0,COUNTIF($A$1:A12,Materiales!$A$2:$A$600)+IF(Materiales!$A$2:$A$600="",1,0),0)),"")} | B13: {=IFERROR(INDEX(Colecciones!$A$2:$A$600,MATCH(0,COUNTIF($B$1:B12,Colecciones!$A$2:$A$600)+IF(Colecciones!$A$2:$A$600="",1,0),0)),"")}
... A600: {=IFERROR(INDEX(Materiales!$A$2:$A$600,MATCH(0,COUNTIF($A$1:A599,Materiales!$A$2:$A$600)+IF(Materiales!$A$2:$A$600="",1,0),0)),"")} | B600: {=IFERROR(INDEX(Colecciones!$A$2:$A$600,MATCH(0,COUNTIF($B$1:B599,Colecciones!$A$2:$A$600)+IF(Colecciones!$A$2:$A$600="",1,0),0)),"")}
